Workbook

Sheet Historical Stock Data
A1: GP Data | D1: DSEX Data
A2: Date | B2: Price | D2: Date | E2: Price
A3: 45988 | B3: 278.4 | D3: 45988 | E3: 5028.14
A4: 45987 | B4: 277.9 | D4: 45987 | E4: 5009.8
A5: 45986 | B5: 277.5 | D5: 45986 | E5: 5018.28
A6: 45985 | B6: 275.2 | D6: 45985 | E6: 5024.86
A7: 45984 | B7: 274 | D7: 45984 | E7: 4915.75
A8: 45981 | B8: 273.3 | D8: 45981 | E8: 4869.01
A9: 45980 | B9: 273.9 | D9: 45980 | E9: 4901.38
A10: 45979 | B10: 272.4 | D10: 45979 | E10: 4846.88
A11: 45978 | B11: 271.9 | D11: 45978 | E11: 4774.96
A12: 45977 | B12: 271.4 | D12: 45977 | E12: 4732.16
A13: 45974 | B13: 277.2 | D13: 45974 | E13: 4702.69
A14: 45973 | B14: 278.5 | D14: 45973 | E14: 4825.33
... A1530: 43599 | B1530: 346.6 | D1530: 43431 | E1530: 5288.54
A1531: 43598 | B1531: 348.1
A1532: 43597 | B1532: 352.4
A1533: 43594 | B1533: 354.1
A1534: 43593 | B1534: 354.6
A1535: 43592 | B1535: 354.4
A1536: 43591 | B1536: 359.4
A1537: 43590 | B1537: 362.5
A1538: 43587 | B1538: 358.2
A1539: 43585 | B1539: 358.7
A1540: 43584 | B1540: 360
A1541: 43583 | B1541: 365.2
A1542: 43580 | B1542: 364.2
... A1639: 43431 | B1639: 366

Sheet Return Calculations
A1: GP | E1: DSEX | J1: GP Return | K1: DSEX Return | M1: Starting Date | N1: 43431 | R1: STEPS
A2: Date | B2: Price | C2: Return | E2: Date | F2: Price | G2: Return | J2: =(B3/B4)-1 -> 0.0017992083 | K2: =(F3/F4)-1 -> 0.0036608248 | M2: Ending Date | N2: =A3 -> 45988 | R2: 1 | S2: 1.Investing.com- Gp historical data 2.Investing.com- DSEX historical data 3. Remove uncommon dates using SQL 4. Calculate daily return using excel formula 5. Remove 0 returns (33, 0 returns in total)
A3: 45988 | B3: =VLOOKUP(A3,'[2]GP Data'!$A$3:$B$1639, 2, FALSE) -> 278.4 | C3: =(B3/B4)-1 -> 0.0017992083 | E3: 45988 | F3: =VLOOKUP(E3,'[2]GP Data'!$D$3:$E$1530, 2, FALSE) -> 5028.14 | G3: =(F3/F4)-1 -> 0.0036608248 | J3: =(B4/B5)-1 -> 0.0014414414 | K3: =(F4/F5)-1 -> -0.001689822 | M3: Range | N3: 7 Years
A4: 45987 | B4: 277.9 | C4: =(B4/B5)-1 -> 0.0014414414 | E4: 45987 | F4: =VLOOKUP(E4,'[2]GP Data'!$D$3:$E$1530, 2, FALSE) -> 5009.8 | G4: =(F4/F5)-1 -> -0.001689822 | J4: =(B5/B6)-1 -> 0.0083575581 | K4: =(F5/F6)-1 -> -0.0013094892
A5: 45986 | B5: =VLOOKUP(A5,'[2]GP Data'!$A$3:$B$1639, 2, FALSE) -> 277.5 | C5: =(B5/B6)-1 -> 0.0083575581 | E5: 45986 | F5: =VLOOKUP(E5,'[2]GP Data'!$D$3:$E$1530, 2, FALSE) -> 5018.28 | G5: =(F5/F6)-1 -> -0.0013094892 | J5: =(B6/B7)-1 -> 0.004379562 | K5: =(F6/F7)-1 -> 0.022196003 | M5: SLOPE | N5: =SLOPE(J2:J1188,K2:K1188) -> 0.85102811
A6: 45985 | B6: =VLOOKUP(A6,'[2]GP Data'!$A$3:$B$1639, 2, FALSE) -> 275.2 | C6: =(B6/B7)-1 -> 0.004379562 | E6: 45985 | F6: =VLOOKUP(E6,'[2]GP Data'!$D$3:$E$1530, 2, FALSE) -> 5024.86 | G6: =(F6/F7)-1 -> 0.022196003 | J6: =(B7/B8)-1 -> 0.002561288 | K6: =(F7/F8)-1 -> 0.0095994874 | M6: R-SQUARE | N6: =RSQ(K2:K1188,J2:J1188) -> 0.29126945 | R6: 2 | S6: GP Return and DSE Return over the 7 years has been used to conjure a scatter plot, comparing the impact of GP return changes due to market fluctuations. The linear equation and R square value has been shown. GP return is y value (dependant variable) and DSEX Return is x variable (Independant variable). The slope value of 0.851 is the beta of GP.
A7: 45984 | B7: =VLOOKUP(A7,'[2]GP Data'!$A$3:$B$1639, 2, FALSE) -> 274 | C7: =(B7/B8)-1 -> 0.002561288 | E7: 45984 | F7: =VLOOKUP(E7,'[2]GP Data'!$D$3:$E$1530, 2, FALSE) -> 4915.75 | G7: =(F7/F8)-1 -> 0.0095994874 | J7: =(B8/B9)-1 -> -0.0021905805 | K7: =(F8/F9)-1 -> -0.0066042625 | M7: ALPHA | N7: =INTERCEPT(K2:K1188,J2:J1188) -> 4.45452e-05
A8: 45981 | B8: =VLOOKUP(A8,'[2]GP Data'!$A$3:$B$1639, 2, FALSE) -> 273.3 | C8: =(B8/B9)-1 -> -0.0021905805 | E8: 45981 | F8: =VLOOKUP(E8,'[2]GP Data'!$D$3:$E$1530, 2, FALSE) -> 4869.01 | G8: =(F8/F9)-1 -> -0.0066042625 | J8: =(B9/B10)-1 -> 0.0055066079 | K8: =(F9/F10)-1 -> 0.011244347
A9: 45980 | B9: =VLOOKUP(A9,'[2]GP Data'!$A$3:$B$1639, 2, FALSE) -> 273.9 | C9: =(B9/B10)-1 -> 0.0055066079 | E9: 45980 | F9: =VLOOKUP(E9,'[2]GP Data'!$D$3:$E$1530, 2, FALSE) -> 4901.38 | G9: =(F9/F10)-1 -> 0.011244347 | J9: =(B10/B11)-1 -> 0.0018389114 | K9: =(F10/F11)-1 -> 0.015061906
A10: 45979 | B10: =VLOOKUP(A10,'[2]GP Data'!$A$3:$B$1639, 2, FALSE) -> 272.4 | C10: =(B10/B11)-1 -> 0.0018389114 | E10: 45979 | F10: =VLOOKUP(E10,'[2]GP Data'!$D$3:$E$1530, 2, FALSE) -> 4846.88 | G10: =(F10/F11)-1 -> 0.015061906 | J10: =(B11/B12)-1 -> 0.0018422992 | K10: =(F11/F12)-1 -> 0.0090444955
A11: 45978 | B11: =VLOOKUP(A11,'[2]GP Data'!$A$3:$B$1639, 2, FALSE) -> 271.9 | C11: =(B11/B12)-1 -> 0.0018422992 | E11: 45978 | F11: =VLOOKUP(E11,'[2]GP Data'!$D$3:$E$1530, 2, FALSE) -> 4774.96 | G11: =(F11/F12)-1 -> 0.0090444955 | J11: =(B12/B13)-1 -> -0.020923521 | K11: =(F12/F13)-1 -> 0.0062666261
A12: 45977 | B12: =VLOOKUP(A12,'[2]GP Data'!$A$3:$B$1639, 2, FALSE) -> 271.4 | C12: =(B12/B13)-1 -> -0.020923521 | E12: 45977 | F12: =VLOOKUP(E12,'[2]GP Data'!$D$3:$E$1530, 2, FALSE) -> 4732.16 | G12: =(F12/F13)-1 -> 0.0062666261 | J12: =(B13/B14)-1 -> -0.0046678636 | K12: =(F13/F14)-1 -> -0.025415878
A13: 45974 | B13: =VLOOKUP(A13,'[2]GP Data'!$A$3:$B$1639, 2, FALSE) -> 277.2 | C13: =(B13/B14)-1 -> -0.0046678636 | E13: 45974 | F13: =VLOOKUP(E13,'[2]GP Data'!$D$3:$E$1530, 2, FALSE) -> 4702.69 | G13: =(F13/F14)-1 -> -0.025415878 | J13: =(B14/B15)-1 -> 0.0028808066 | K13: =(F14/F15)-1 -> -0.0097357355
A14: 45973 | B14: =VLOOKUP(A14,'[2]GP Data'!$A$3:$B$1639, 2, FALSE) -> 278.5 | C14: =(B14/B15)-1 -> 0.0028808066 | E14: 45973 | F14: =VLOOKUP(E14,'[2]GP Data'!$D$3:$E$1530, 2, FALSE) -> 4825.33 | G14: =(F14/F15)-1 -> -0.0097357355 | J14: =(B15/B16)-1 -> 0.0014424811 | K14: =(F15/F16)-1 -> 0.0024728694
A15: 45972 | B15: =VLOOKUP(A15,'[2]GP Data'!$A$3:$B$1639, 2, FALSE) -> 277.7 | C15: =(B15/B16)-1 -> 0.0014424811 | E15: 45972 | F15: =VLOOKUP(E15,'[2]GP Data'!$D$3:$E$1530, 2, FALSE) -> 4872.77 | G15: =(F15/F16)-1 -> 0.0024728694 | J15: =(B16/B17)-1 -> -0.013518321 | K15: =(F16/F17)-1 -> -0.0079960326
A16: 45971 | B16: =VLOOKUP(A16,'[2]GP Data'!$A$3:$B$1639, 2, FALSE) -> 277.3 | C16: =(B16/B17)-1 -> -0.013518321 | E16: 45971 | F16: =VLOOKUP(E16,'[2]GP Data'!$D$3:$E$1530, 2, FALSE) -> 4860.75 | G16: =(F16/F17)-1 -> -0.0079960326 | J16: =(B17/B18)-1 -> -0.0060113154 | K16: =(F17/F18)-1 -> -0.013689779
A17: 45970 | B17: =VLOOKUP(A17,'[2]GP Data'!$A$3:$B$1639, 2, FALSE) -> 281.1 | C17: =(B17/B18)-1 -> -0.0060113154 | E17: 45970 | F17: =VLOOKUP(E17,'[2]GP Data'!$D$3:$E$1530, 2, FALSE) -> 4899.93 | G17: =(F17/F18)-1 -> -0.013689779 | J17: =(B18/B19)-1 -> -0.0052761168 | K17: =(F18/F19)-1 -> -0.0037999635
A18: 45967 | B18: =VLOOKUP(A18,'[2]GP Data'!$A$3:$B$1639, 2, FALSE) -> 282.8 | C18: =(B18/B19)-1 -> -0.0052761168 | E18: 45967 | F18: =VLOOKUP(E18,'[2]GP Data'!$D$3:$E$1530, 2, FALSE) -> 4967.94 | G18: =(F18/F19)-1 -> -0.0037999635 | J18: =(B19/B20)-1 -> 0.003529827 | K18: =(F19/F20)-1 -> -0.0064115464
A19: 45966 | B19: =VLOOKUP(A19,'[2]GP Data'!$A$3:$B$1639, 2, FALSE) -> 284.3 | C19: =(B19/B20)-1 -> 0.003529827 | E19: 45966 | F19: =VLOOKUP(E19,'[2]GP Data'!$D$3:$E$1530, 2, FALSE) -> 4986.89 | G19: =(F19/F20)-1 -> -0.0064115464 | J19: =(B20/B21)-1 -> 0.0078263963 | K19: =(F20/F21)-1 -> -0.0082868834
... A35: 45944 | B35: =VLOOKUP(A35,'[2]GP Data'!$A$3:$B$1639, 2, FALSE) -> 292.4 | C35: =(B35/B36)-1 -> -0.0054421769 | E35: 45944 | F35: =VLOOKUP(E35,'[2]GP Data'!$D$3:$E$1530, 2, FALSE) -> 5197.27 | G35: =(F35/F36)-1 -> -0.0058304242 | J35: =(B36/B37)-1 -> 0.0017035775 | K35: =(F36/F37)-1 -> 0.0048611618
A36: 45943 | B36: =VLOOKUP(A36,'[2]GP Data'!$A$3:$B$1639, 2, FALSE) -> 294 | C36: =(B36/B37)-1 -> 0.0017035775 | E36: 45943 | F36: =VLOOKUP(E36,'[2]GP Data'!$D$3:$E$1530, 2, FALSE) -> 5227.75 | G36: =(F36/F37)-1 -> 0.0048611618 | J36: =(B37/B38)-1 -> -0.0027183146 | K36: =(F37/F38)-1 -> -0.015379316 | M36: Beta | N36: Source | O36: Data Frame
A37: 45942 | B37: =VLOOKUP(A37,'[2]GP Data'!$A$3:$B$1639, 2, FALSE) -> 293.5 | C37: =(B37/B38)-1 -> -0.0027183146 | E37: 45942 | F37: =VLOOKUP(E37,'[2]GP Data'!$D$3:$E$1530, 2, FALSE) -> 5202.46 | G37: =(F37/F38)-1 -> -0.015379316 | J37: =(B38/B39)-1 -> 0.00033990483 | K37: =(F38/F39)-1 -> -0.010142641 | M37: 0.48 | N37: https://www.amarstock.com/stock/GP | O37: 10 - 15 years
A38: 45939 | B38: =VLOOKUP(A38,'[2]GP Data'!$A$3:$B$1639, 2, FALSE) -> 294.3 | C38: =(B38/B39)-1 -> 0.00033990483 | E38: 45939 | F38: =VLOOKUP(E38,'[2]GP Data'!$D$3:$E$1530, 2, FALSE) -> 5283.72 | G38: =(F38/F39)-1 -> -0.010142641 | J38: =(B39/B40)-1 -> -0.0016966407 | K38: =(F39/F40)-1 -> -0.0072791519 | M38: 0.98 | N38: https://biniyog.com.bd/company/gp
A39: 45938 | B39: =VLOOKUP(A39,'[2]GP Data'!$A$3:$B$1639, 2, FALSE) -> 294.2 | C39: =(B39/B40)-1 -> -0.0016966407 | E39: 45938 | F39: =VLOOKUP(E39,'[2]GP Data'!$D$3:$E$1530, 2, FALSE) -> 5337.86 | G39: =(F39/F40)-1 -> -0.0072791519 | J39: =(B40/B41)-1 -> -0.011405569 | K39: =(F40/F41)-1 -> -0.0085993908 | M39: 0.7 | N39: https://dspace.bracu.ac.bd:8443/xmlui/bitstream/handle/10361/18020/17104210_BBA.pdf?sequence=1&isAllowed=y | O39: 2016 - 2020
A40: 45937 | B40: =VLOOKUP(A40,'[2]GP Data'!$A$3:$B$1639, 2, FALSE) -> 294.7 | C40: =(B40/B41)-1 -> -0.011405569 | E40: 45937 | F40: =VLOOKUP(E40,'[2]GP Data'!$D$3:$E$1530, 2, FALSE) -> 5377 | G40: =(F40/F41)-1 -> -0.0085993908 | J40: =(B41/B42)-1 -> -0.0020087044 | K40: =(F41/F42)-1 -> -0.0044037499 | M40: 0.13 | N40: https://www.investing.com/pro/DSE:GP/explorer/beta | O40: 5 years
A41: 45936 | B41: =VLOOKUP(A41,'[2]GP Data'!$A$3:$B$1639, 2, FALSE) -> 298.1 | C41: =(B41/B42)-1 -> -0.0020087044 | E41: 45936 | F41: =VLOOKUP(E41,'[2]GP Data'!$D$3:$E$1530, 2, FALSE) -> 5423.64 | G41: =(F41/F42)-1 -> -0.0044037499 | J41: =(B42/B43)-1 -> -0.0010033445 | K41: =(F42/F43)-1 -> 0.0058791054
A42: 45935 | B42: =VLOOKUP(A42,'[2]GP Data'!$A$3:$B$1639, 2, FALSE) -> 298.7 | C42: =(B42/B43)-1 -> -0.0010033445 | E42: 45935 | F42: =VLOOKUP(E42,'[2]GP Data'!$D$3:$E$1530, 2, FALSE) -> 5447.63 | G42: =(F42/F43)-1 -> 0.0058791054 | J42: =(B43/B44)-1 -> 0.0033557047 | K42: =(F43/F44)-1 -> 0.0048257999
A43: 45930 | B43: =VLOOKUP(A43,'[2]GP Data'!$A$3:$B$1639, 2, FALSE) -> 299 | C43: =(B43/B44)-1 -> 0.0033557047 | E43: 45930 | F43: =VLOOKUP(E43,'[2]GP Data'!$D$3:$E$1530, 2, FALSE) -> 5415.79 | G43: =(F43/F44)-1 -> 0.0048257999 | J43: =(B44/B45)-1 -> -0.0036776998 | K43: =(F44/F45)-1 -> 0.0018029472
A44: 45929 | B44: =VLOOKUP(A44,'[2]GP Data'!$A$3:$B$1639, 2, FALSE) -> 298 | C44: =(B44/B45)-1 -> -0.0036776998 | E44: 45929 | F44: =VLOOKUP(E44,'[2]GP Data'!$D$3:$E$1530, 2, FALSE) -> 5389.78 | G44: =(F44/F45)-1 -> 0.0018029472 | J44: =(B45/B46)-1 -> 0.0023458445 | K44: =(F45/F46)-1 -> -0.0064726055
A45: 45928 | B45: =VLOOKUP(A45,'[2]GP Data'!$A$3:$B$1639, 2, FALSE) -> 299.1 | C45: =(B45/B46)-1 -> 0.0023458445 | E45: 45928 | F45: =VLOOKUP(E45,'[2]GP Data'!$D$3:$E$1530, 2, FALSE) -> 5380.08 | G45: =(F45/F46)-1 -> -0.0064726055 | J45: =(B46/B47)-1 -> -0.002006689 | K45: =(F46/F47)-1 -> 0.0041686369
A46: 45925 | B46: =VLOOKUP(A46,'[2]GP Data'!$A$3:$B$1639, 2, FALSE) -> 298.4 | C46: =(B46/B47)-1 -> -0.002006689 | E46: 45925 | F46: =VLOOKUP(E46,'[2]GP Data'!$D$3:$E$1530, 2, FALSE) -> 5415.13 | G46: =(F46/F47)-1 -> 0.0041686369 | J46: =(B47/B48)-1 -> 0.0016750419 | K46: =(F47/F48)-1 -> 0.0084488553
A47: 45924 | B47: =VLOOKUP(A47,'[2]GP Data'!$A$3:$B$1639, 2, FALSE) -> 299 | C47: =(B47/B48)-1 -> 0.0016750419 | E47: 45924 | F47: =VLOOKUP(E47,'[2]GP Data'!$D$3:$E$1530, 2, FALSE) -> 5392.65 | G47: =(F47/F48)-1 -> 0.0084488553 | J47: =(B48/B49)-1 -> -0.0053315561 | K47: =(F48/F49)-1 -> 0.0019354935
A48: 45923 | B48: =VLOOKUP(A48,'[2]GP Data'!$A$3:$B$1639, 2, FALSE) -> 298.5 | C48: =(B48/B49)-1 -> -0.0053315561 | E48: 45923 | F48: =VLOOKUP(E48,'[2]GP Data'!$D$3:$E$1530, 2, FALSE) -> 5347.47 | G48: =(F48/F49)-1 -> 0.0019354935 | J48: =(B49/B50)-1 -> -0.00066600067 | K48: =(F49/F50)-1 -> -0.0083075522
A49: 45922 | B49: =VLOOKUP(A49,'[2]GP Data'!$A$3:$B$1639, 2, FALSE) -> 300.1 | C49: =(B49/B50)-1 -> -0.00066600067 | E49: 45922 | F49: =VLOOKUP(E49,'[2]GP Data'!$D$3:$E$1530, 2, FALSE) -> 5337.14 | G49: =(F49/F50)-1 -> -0.0083075522 | J49: =(B50/B51)-1 -> -0.0026569246 | K49: =(F50/F51)-1 -> -0.012491904
A50: 45921 | B50: =VLOOKUP(A50,'[2]GP Data'!$A$3:$B$1639, 2, FALSE) -> 300.3 | C50: =(B50/B51)-1 -> -0.0026569246 | E50: 45921 | F50: =VLOOKUP(E50,'[2]GP Data'!$D$3:$E$1530, 2, FALSE) -> 5381.85 | G50: =(F50/F51)-1 -> -0.012491904 | J50: =(B51/B52)-1 -> -0.0023194168 | K50: =(F51/F52)-1 -> -0.010831983
A51: 45918 | B51: =VLOOKUP(A51,'[2]GP Data'!$A$3:$B$1639, 2, FALSE) -> 301.1 | C51: =(B51/B52)-1 -> -0.0023194168 | E51: 45918 | F51: =VLOOKUP(E51,'[2]GP Data'!$D$3:$E$1530, 2, FALSE) -> 5449.93 | G51: =(F51/F52)-1 -> -0.010831983 | J51: =(B52/B53)-1 -> 0.0026578073 | K51: =(F52/F53)-1 -> 0.0063729287
A52: 45916 | B52: =VLOOKUP(A52,'[2]GP Data'!$A$3:$B$1639, 2, FALSE) -> 301.8 | C52: =(B52/B53)-1 -> 0.0026578073 | E52: 45916 | F52: =VLOOKUP(E52,'[2]GP Data'!$D$3:$E$1530, 2, FALSE) -> 5509.61 | G52: =(F52/F53)-1 -> 0.0063729287 | J52: =(B53/B54)-1 -> 0.0036678893 | K52: =(F53/F54)-1 -> 0.0011648852
... A65: 45897 | B65: =VLOOKUP(A65,'[2]GP Data'!$A$3:$B$1639, 2, FALSE) -> 305.4 | C65: =(B65/B66)-1 -> 0.02277294 | E65: 45897 | F65: =VLOOKUP(E65,'[2]GP Data'!$D$3:$E$1530, 2, FALSE) -> 5517.95 | G65: =(F65/F66)-1 -> 0.012685292 | J65: =(B66/B67)-1 -> -0.00033478406 | K65: =(F66/F67)-1 -> -0.0012043113
A66: 45895 | B66: =VLOOKUP(A66,'[2]GP Data'!$A$3:$B$1639, 2, FALSE) -> 298.6 | C66: =(B66/B67)-1 -> -0.00033478406 | E66: 45895 | F66: 5448.83 | G66: =(F66/F67)-1 -> -0.0012043113 | J66: =(B67/B68)-1 -> 0.0070802428 | K66: =(F67/F68)-1 -> 0.012289462
A67: 45894 | B67: =VLOOKUP(A67,'[2]GP Data'!$A$3:$B$1639, 2, FALSE) -> 298.7 | C67: =(B67/B68)-1 -> 0.0070802428 | E67: 45894 | F67: =VLOOKUP(E67,'[2]GP Data'!$D$3:$E$1530, 2, FALSE) -> 5455.4 | G67: =(F67/F68)-1 -> 0.012289462 | J67: =(B68/B69)-1 -> -0.0086898396 | K67: =(F68/F69)-1 -> 0.0026437406
A68: 45893 | B68: =VLOOKUP(A68,'[2]GP Data'!$A$3:$B$1639, 2, FALSE) -> 296.6 | C68: =(B68/B69)-1 -> -0.0086898396 | E68: 45893 | F68: =VLOOKUP(E68,'[2]GP Data'!$D$3:$E$1530, 2, FALSE) -> 5389.17 | G68: =(F68/F69)-1 -> 0.0026437406 | J68: =(B69/B70)-1 -> -0.0086149768 | K68: =(F69/F70)-1 -> -0.00082722826
A69: 45890 | B69: =VLOOKUP(A69,'[2]GP Data'!$A$3:$B$1639, 2, FALSE) -> 299.2 | C69: =(B69/B70)-1 -> -0.0086149768 | E69: 45890 | F69: =VLOOKUP(E69,'[2]GP Data'!$D$3:$E$1530, 2, FALSE) -> 5374.96 | G69: =(F69/F70)-1 -> -0.00082722826 | J69: =(B70/B71)-1 -> -0.00099304866 | K69: =(F70/F71)-1 -> -0.0058197342
A70: 45889 | B70: =VLOOKUP(A70,'[2]GP Data'!$A$3:$B$1639, 2, FALSE) -> 301.8 | C70: =(B70/B71)-1 -> -0.00099304866 | E70: 45889 | F70: =VLOOKUP(E70,'[2]GP Data'!$D$3:$E$1530, 2, FALSE) -> 5379.41 | G70: =(F70/F71)-1 -> -0.0058197342 | J70: =(B71/B72)-1 -> -0.0095081967 | K70: =(F71/F72)-1 -> -0.0016623892
A71: 45888 | B71: =VLOOKUP(A71,'[2]GP Data'!$A$3:$B$1639, 2, FALSE) -> 302.1 | C71: =(B71/B72)-1 -> -0.0095081967 | E71: 45888 | F71: =VLOOKUP(E71,'[2]GP Data'!$D$3:$E$1530, 2, FALSE) -> 5410.9 | G71: =(F71/F72)-1 -> -0.0016623892 | J71: =(B72/B73)-1 -> 0.0039499671 | K71: =(F72/F73)-1 -> 0.0034101702
A72: 45887 | B72: =VLOOKUP(A72,'[2]GP Data'!$A$3:$B$1639, 2, FALSE) -> 305 | C72: =(B72/B73)-1 -> 0.0039499671 | E72: 45887 | F72: =VLOOKUP(E72,'[2]GP Data'!$D$3:$E$1530, 2, FALSE) -> 5419.91 | G72: =(F72/F73)-1 -> 0.0034101702 | J72: =(B73/B74)-1 -> -0.0032808399 | K72: =(F73/F74)-1 -> 0.0095771226
A73: 45886 | B73: =VLOOKUP(A73,'[2]GP Data'!$A$3:$B$1639, 2, FALSE) -> 303.8 | C73: =(B73/B74)-1 -> -0.0032808399 | E73: 45886 | F73: =VLOOKUP(E73,'[2]GP Data'!$D$3:$E$1530, 2, FALSE) -> 5401.49 | G73: =(F73/F74)-1 -> 0.0095771226 | J73: =(B74/B75)-1 -> -0.033301618 | K73: =(F74/F75)-1 -> 0.0065469528
A74: 45883 | B74: =VLOOKUP(A74,'[2]GP Data'!$A$3:$B$1639, 2, FALSE) -> 304.8 | C74: =(B74/B75)-1 -> -0.033301618 | E74: 45883 | F74: =VLOOKUP(E74,'[2]GP Data'!$D$3:$E$1530, 2, FALSE) -> 5350.25 | G74: =(F74/F75)-1 -> 0.0065469528 | J74: =(B75/B76)-1 -> -0.0037914692 | K74: =(F75/F76)-1 -> -0.0053517463
A75: 45881 | B75: =VLOOKUP(A75,'[2]GP Data'!$A$3:$B$1639, 2, FALSE) -> 315.3 | C75: =(B75/B76)-1 -> -0.0037914692 | E75: 45881 | F75: =VLOOKUP(E75,'[2]GP Data'!$D$3:$E$1530, 2, FALSE) -> 5315.45 | G75: =(F75/F76)-1 -> -0.0053517463 | J75: =(B76/B77)-1 -> 0.0009487666 | K75: =(F76/F77)-1 -> -0.0013044218
A76: 45880 | B76: =VLOOKUP(A76,'[2]GP Data'!$A$3:$B$1639, 2, FALSE) -> 316.5 | C76: =(B76/B77)-1 -> 0.0009487666 | E76: 45880 | F76: =VLOOKUP(E76,'[2]GP Data'!$D$3:$E$1530, 2, FALSE) -> 5344.05 | G76: =(F76/F77)-1 -> -0.0013044218 | J76: =(B77/B78)-1 -> 0.0015837821 | K76: =(F77/F78)-1 -> -0.010547201
A77: 45879 | B77: =VLOOKUP(A77,'[2]GP Data'!$A$3:$B$1639, 2, FALSE) -> 316.2 | C77: =(B77/B78)-1 -> 0.0015837821 | E77: 45879 | F77: =VLOOKUP(E77,'[2]GP Data'!$D$3:$E$1530, 2, FALSE) -> 5351.03 | G77: =(F77/F78)-1 -> -0.010547201 | J77: =(B78/B79)-1 -> -0.0041009464 | K77: =(F78/F79)-1 -> -0.011531375
A78: 45876 | B78: =VLOOKUP(A78,'[2]GP Data'!$A$3:$B$1639, 2, FALSE) -> 315.7 | C78: =(B78/B79)-1 -> -0.0041009464 | E78: 45876 | F78: =VLOOKUP(E78,'[2]GP Data'!$D$3:$E$1530, 2, FALSE) -> 5408.07 | G78: =(F78/F79)-1 -> -0.011531375 | J78: =(B79/B80)-1 -> -0.00063051702 | K78: =(F79/F80)-1 -> -0.0026887062
... A123: 45802 | B123: =VLOOKUP(A123,'[2]GP Data'!$A$3:$B$1639, 2, FALSE) -> 272.3 | C123: =(B123/B124)-1 -> -0.034054629 | E123: 45802 | F123: =VLOOKUP(E123,'[2]GP Data'!$D$3:$E$1530, 2, FALSE) -> 4736.34 | G123: =(F123/F124)-1 -> -0.010194102 | J123: =(B124/B125)-1 -> -0.022538141 | K123: =(F124/F125)-1 -> -0.0033740721
A124: 45799 | B124: =VLOOKUP(A124,'[2]GP Data'!$A$3:$B$1639, 2, FALSE) -> 281.9 | C124: =(B124/B125)-1 -> -0.022538141 | E124: 45799 | F124: 4785.12 | G124: =(F124/F125)-1 -> -0.0033740721 | J124: =(B125/B126)-1 -> -0.020713073 | K124: =(F125/F126)-1 -> 0.0013075985
A125: 45798 | B125: =VLOOKUP(A125,'[2]GP Data'!$A$3:$B$1639, 2, FALSE) -> 288.4 | C125: =(B125/B126)-1 -> -0.020713073 | E125: 45798 | F125: =VLOOKUP(E125,'[2]GP Data'!$D$3:$E$1530, 2, FALSE) -> 4801.32 | G125: =(F125/F126)-1 -> 0.0013075985 | J125: =(B126/B127)-1 -> 0.0013600816 | K125: =(F126/F127)-1 -> 0.0039193272
A126: 45797 | B126: =VLOOKUP(A126,'[2]GP Data'!$A$3:$B$1639, 2, FALSE) -> 294.5 | C126: =(B126/B127)-1 -> 0.0013600816 | E126: 45797 | F126: =VLOOKUP(E126,'[2]GP Data'!$D$3:$E$1530, 2, FALSE) -> 4795.05 | G126: =(F126/F127)-1 -> 0.0039193272 | J126: =(B127/B128)-1 -> -0.0070898042 | K126: =(F127/F128)-1 -> -0.0030807186
A127: 45796 | B127: =VLOOKUP(A127,'[2]GP Data'!$A$3:$B$1639, 2, FALSE) -> 294.1 | C127: =(B127/B128)-1 -> -0.0070898042 | E127: 45796 | F127: =VLOOKUP(E127,'[2]GP Data'!$D$3:$E$1530, 2, FALSE) -> 4776.33 | G127: =(F127/F128)-1 -> -0.0030807186 | J127: =(B128/B129)-1 -> 0.004408274 | K127: =(F128/F129)-1 -> 0.0021062451
A128: 45795 | B128: =VLOOKUP(A128,'[2]GP Data'!$A$3:$B$1639, 2, FALSE) -> 296.2 | C128: =(B128/B129)-1 -> 0.004408274 | E128: 45795 | F128: =VLOOKUP(E128,'[2]GP Data'!$D$3:$E$1530, 2, FALSE) -> 4791.09 | G128: =(F128/F129)-1 -> 0.0021062451 | J128: =(B129/B130)-1 -> -0.0067362748 | K128: =(F129/F130)-1 -> -0.011287121
A129: 45792 | B129: =VLOOKUP(A129,'[2]GP Data'!$A$3:$B$1639, 2, FALSE) -> 294.9 | C129: =(B129/B130)-1 -> -0.0067362748 | E129: 45792 | F129: =VLOOKUP(E129,'[2]GP Data'!$D$3:$E$1530, 2, FALSE) -> 4781.02 | G129: =(F129/F130)-1 -> -0.011287121 | J129: =(B130/B131)-1 -> -0.00033670034 | K129: =(F130/F131)-1 -> -0.0079965864
A130: 45791 | B130: =VLOOKUP(A130,'[2]GP Data'!$A$3:$B$1639, 2, FALSE) -> 296.9 | C130: =(B130/B131)-1 -> -0.00033670034 | E130: 45791 | F130: =VLOOKUP(E130,'[2]GP Data'!$D$3:$E$1530, 2, FALSE) -> 4835.6 | G130: =(F130/F131)-1 -> -0.0079965864 | J130: =(B131/B132)-1 -> -0.0036900369 | K130: =(F131/F132)-1 -> -0.0095457538
A131: 45790 | B131: =VLOOKUP(A131,'[2]GP Data'!$A$3:$B$1639, 2, FALSE) -> 297 | C131: =(B131/B132)-1 -> -0.0036900369 | E131: 45790 | F131: =VLOOKUP(E131,'[2]GP Data'!$D$3:$E$1530, 2, FALSE) -> 4874.58 | G131: =(F131/F132)-1 -> -0.0095457538 | J131: =(B132/B133)-1 -> 0.00033557047 | K131: =(F132/F133)-1 -> 0.0039328639
A132: 45789 | B132: =VLOOKUP(A132,'[2]GP Data'!$A$3:$B$1639, 2, FALSE) -> 298.1 | C132: =(B132/B133)-1 -> 0.00033557047 | E132: 45789 | F132: =VLOOKUP(E132,'[2]GP Data'!$D$3:$E$1530, 2, FALSE) -> 4921.56 | G132: =(F132/F133)-1 -> 0.0039328639 | J132: =(B133/B134)-1 -> 0.002354524 | K132: =(F133/F134)-1 -> 0.020793683
A133: 45785 | B133: =VLOOKUP(A133,'[2]GP Data'!$A$3:$B$1639, 2, FALSE) -> 298 | C133: =(B133/B134)-1 -> 0.002354524 | E133: 45785 | F133: =VLOOKUP(E133,'[2]GP Data'!$D$3:$E$1530, 2, FALSE) -> 4902.28 | G133: =(F133/F134)-1 -> 0.020793683 | J133: =(B134/B135)-1 -> -0.015888779 | K133: =(F134/F135)-1 -> -0.030153098
A134: 45784 | B134: =VLOOKUP(A134,'[2]GP Data'!$A$3:$B$1639, 2, FALSE) -> 297.3 | C134: =(B134/B135)-1 -> -0.015888779 | E134: 45784 | F134: =VLOOKUP(E134,'[2]GP Data'!$D$3:$E$1530, 2, FALSE) -> 4802.42 | G134: =(F134/F135)-1 -> -0.030153098 | J134: =(B135/B136)-1 -> -0.006576784 | K134: =(F135/F136)-1 -> -0.0026064169
A135: 45783 | B135: =VLOOKUP(A135,'[2]GP Data'!$A$3:$B$1639, 2, FALSE) -> 302.1 | C135: =(B135/B136)-1 -> -0.006576784 | E135: 45783 | F135: =VLOOKUP(E135,'[2]GP Data'!$D$3:$E$1530, 2, FALSE) -> 4951.73 | G135: =(F135/F136)-1 -> -0.0026064169 | J135: =(B136/B137)-1 -> 0.012991339 | K135: =(F136/F137)-1 -> 0.0016988651
A136: 45782 | B136: =VLOOKUP(A136,'[2]GP Data'!$A$3:$B$1639, 2, FALSE) -> 304.1 | C136: =(B136/B137)-1 -> 0.012991339 | E136: 45782 | F136: =VLOOKUP(E136,'[2]GP Data'!$D$3:$E$1530, 2, FALSE) -> 4964.67 | G136: =(F136/F137)-1 -> 0.0016988651 | J136: =(B137/B138)-1 -> 0.0020026702 | K136: =(F137/F138)-1 -> 0.0077939454
... A196: 45685 | B196: =VLOOKUP(A196,'[2]GP Data'!$A$3:$B$1639, 2, FALSE) -> 331.7 | C196: =(B196/B197)-1 -> 0.0027206771 | E196: 45685 | F196: =VLOOKUP(E196,'[2]GP Data'!$D$3:$E$1530, 2, FALSE) -> 5126.42 | G196: =(F196/F197)-1 -> -0.00070954336 | J196: =(B197/B198)-1 -> -0.0086904405 | K196: =(F197/F198)-1 -> -0.0070588964
A197: 45684 | B197: =VLOOKUP(A197,'[2]GP Data'!$A$3:$B$1639, 2, FALSE) -> 330.8 | C197: =(B197/B198)-1 -> -0.0086904405 | E197: 45684 | F197: 5130.06 | G197: =(F197/F198)-1 -> -0.0070588964 | J197: =(B198/B199)-1 -> -0.0059577003 | K197: =(F198/F199)-1 -> -0.0020686698
A198: 45680 | B198: =VLOOKUP(A198,'[2]GP Data'!$A$3:$B$1639, 2, FALSE) -> 333.7 | C198: =(B198/B199)-1 -> -0.0059577003 | E198: 45680 | F198: =VLOOKUP(E198,'[2]GP Data'!$D$3:$E$1530, 2, FALSE) -> 5166.53 | G198: =(F198/F199)-1 -> -0.0020686698 | J198: =(B199/B200)-1 -> -0.00029779631 | K198: =(F199/F200)-1 -> -0.0048783113
A199: 45679 | B199: =VLOOKUP(A199,'[2]GP Data'!$A$3:$B$1639, 2, FALSE) -> 335.7 | C199: =(B199/B200)-1 -> -0.00029779631 | E199: 45679 | F199: =VLOOKUP(E199,'[2]GP Data'!$D$3:$E$1530, 2, FALSE) -> 5177.24 | G199: =(F199/F200)-1 -> -0.0048783113 | J199: =(B200/B201)-1 -> 0.008105674 | K199: =(F200/F201)-1 -> 0.0013068172
A200: 45678 | B200: =VLOOKUP(A200,'[2]GP Data'!$A$3:$B$1639, 2, FALSE) -> 335.8 | C200: =(B200/B201)-1 -> 0.008105674 | E200: 45678 | F200: =VLOOKUP(E200,'[2]GP Data'!$D$3:$E$1530, 2, FALSE) -> 5202.62 | G200: =(F200/F201)-1 -> 0.0013068172 | J200: =(B201/B202)-1 -> 0.0060404712 | K200: =(F201/F202)-1 -> 0.012059011
A201: 45677 | B201: =VLOOKUP(A201,'[2]GP Data'!$A$3:$B$1639, 2, FALSE) -> 333.1 | C201: =(B201/B202)-1 -> 0.0060404712 | E201: 45677 | F201: =VLOOKUP(E201,'[2]GP Data'!$D$3:$E$1530, 2, FALSE) -> 5195.83 | G201: =(F201/F202)-1 -> 0.012059011 | J201: =(B202/B203)-1 -> 0.0051608986 | K201: =(F202/F203)-1 -> -0.0016723319
A202: 45673 | B202: =VLOOKUP(A202,'[2]GP Data'!$A$3:$B$1639, 2, FALSE) -> 331.1 | C202: =(B202/B203)-1 -> 0.0051608986 | E202: 45673 | F202: =VLOOKUP(E202,'[2]GP Data'!$D$3:$E$1530, 2, FALSE) -> 5133.92 | G202: =(F202/F203)-1 -> -0.0016723319 | J202: =(B203/B204)-1 -> -0.010513668 | K202: =(F203/F204)-1 -> -0.0016210854
A203: 45672 | B203: =VLOOKUP(A203,'[2]GP Data'!$A$3:$B$1639, 2, FALSE) -> 329.4 | C203: =(B203/B204)-1 -> -0.010513668 | E203: 45672 | F203: =VLOOKUP(E203,'[2]GP Data'!$D$3:$E$1530, 2, FALSE) -> 5142.52 | G203: =(F203/F204)-1 -> -0.0016210854 | J203: =(B204/B205)-1 -> -0.018283692 | K203: =(F204/F205)-1 -> -0.00019604494
A204: 45671 | B204: =VLOOKUP(A204,'[2]GP Data'!$A$3:$B$1639, 2, FALSE) -> 332.9 | C204: =(B204/B205)-1 -> -0.018283692 | E204: 45671 | F204: =VLOOKUP(E204,'[2]GP Data'!$D$3:$E$1530, 2, FALSE) -> 5150.87 | G204: =(F204/F205)-1 -> -0.00019604494 | J204: =(B205/B206)-1 -> 0.020156438 | K204: =(F205/F206)-1 -> -0.0081914666
A205: 45670 | B205: =VLOOKUP(A205,'[2]GP Data'!$A$3:$B$1639, 2, FALSE) -> 339.1 | C205: =(B205/B206)-1 -> 0.020156438 | E205: 45670 | F205: =VLOOKUP(E205,'[2]GP Data'!$D$3:$E$1530, 2, FALSE) -> 5151.88 | G205: =(F205/F206)-1 -> -0.0081914666 | J205: =(B206/B207)-1 -> 0.017447199 | K205: =(F206/F207)-1 -> 0.0018187078
A206: 45666 | B206: =VLOOKUP(A206,'[2]GP Data'!$A$3:$B$1639, 2, FALSE) -> 332.4 | C206: =(B206/B207)-1 -> 0.017447199 | E206: 45666 | F206: =VLOOKUP(E206,'[2]GP Data'!$D$3:$E$1530, 2, FALSE) -> 5194.43 | G206: =(F206/F207)-1 -> 0.0018187078 | J206: =(B207/B208)-1 -> 0.0018399264 | K206: =(F207/F208)-1 -> -0.0011135128
A207: 45665 | B207: =VLOOKUP(A207,'[2]GP Data'!$A$3:$B$1639, 2, FALSE) -> 326.7 | C207: =(B207/B208)-1 -> 0.0018399264 | E207: 45665 | F207: =VLOOKUP(E207,'[2]GP Data'!$D$3:$E$1530, 2, FALSE) -> 5185 | G207: =(F207/F208)-1 -> -0.0011135128 | J207: =(B208/B209)-1 -> 0.0027675277 | K207: =(F208/F209)-1 -> -0.0015503458
A208: 45664 | B208: =VLOOKUP(A208,'[2]GP Data'!$A$3:$B$1639, 2, FALSE) -> 326.1 | C208: =(B208/B209)-1 -> 0.0027675277 | E208: 45664 | F208: =VLOOKUP(E208,'[2]GP Data'!$D$3:$E$1530, 2, FALSE) -> 5190.78 | G208: =(F208/F209)-1 -> -0.0015503458 | J208: =(B209/B210)-1 -> 0.0030845157 | K208: =(F209/F210)-1 -> -0.00015001096
A209: 45663 | B209: =VLOOKUP(A209,'[2]GP Data'!$A$3:$B$1639, 2, FALSE) -> 325.2 | C209: =(B209/B210)-1 -> 0.0030845157 | E209: 45663 | F209: =VLOOKUP(E209,'[2]GP Data'!$D$3:$E$1530, 2, FALSE) -> 5198.84 | G209: =(F209/F210)-1 -> -0.00015001096 | J209: =(B210/B211)-1 -> -0.002768379 | K209: =(F210/F211)-1 -> -0.0035529765
... A301: 45481 | B301: =VLOOKUP(A301,'[2]GP Data'!$A$3:$B$1639, 2, FALSE) -> 248.8 | C301: =(B301/B302)-1 -> 0.013029316 | E301: 45481 | F301: =VLOOKUP(E301,'[2]GP Data'!$D$3:$E$1530, 2, FALSE) -> 5564.63 | G301: =(F301/F302)-1 -> 0.012199958 | J301: =(B302/B303)-1 -> 0.022481266 | K301: =(F302/F303)-1 -> 0.023022643
A302: 45477 | B302: 245.6 | C302: =(B302/B303)-1 -> 0.022481266 | E302: 45477 | F302: 5497.56 | G302: =(F302/F303)-1 -> 0.023022643 | J302: =(B303/B304)-1 -> -0.01557377 | K302: =(F303/F304)-1 -> 0.0063012739
A303: 45476 | B303: 240.2 | C303: =(B303/B304)-1 -> -0.01557377 | E303: 45476 | F303: 5373.84 | G303: =(F303/F304)-1 -> 0.0063012739 | J303: =(B304/B305)-1 -> 0.010770505 | K303: =(F304/F305)-1 -> -0.002841986
A304: 45475 | B304: 244 | C304: =(B304/B305)-1 -> 0.010770505 | E304: 45475 | F304: 5340.19 | G304: =(F304/F305)-1 -> -0.002841986 | J304: =(B305/B306)-1 -> 0.022015241 | K304: =(F305/F306)-1 -> 0.00993641
A305: 45470 | B305: 241.4 | C305: =(B305/B306)-1 -> 0.022015241 | E305: 45470 | F305: 5355.41 | G305: =(F305/F306)-1 -> 0.00993641 | J305: =(B306/B307)-1 -> 0.032794053 | K305: =(F306/F307)-1 -> 0.011614242
A306: 45469 | B306: 236.2 | C306: =(B306/B307)-1 -> 0.032794053 | E306: 45469 | F306: 5302.72 | G306: =(F306/F307)-1 -> 0.011614242 | J306: =(B307/B308)-1 -> 0.0021910605 | K306: =(F307/F308)-1 -> 0.0041473586
A307: 45468 | B307: 228.7 | C307: =(B307/B308)-1 -> 0.0021910605 | E307: 45468 | F307: 5241.84 | G307: =(F307/F308)-1 -> 0.0041473586 | J307: =(B308/B309)-1 -> 0.014673188 | K307: =(F308/F309)-1 -> -0.0045651042
A308: 45467 | B308: 228.2 | C308: =(B308/B309)-1 -> 0.014673188 | E308: 45467 | F308: 5220.19 | G308: =(F308/F309)-1 -> -0.0045651042 | J308: =(B309/B310)-1 -> 0.012151215 | K308: =(F309/F310)-1 -> 0.016032534
A309: 45463 | B309: 224.9 | C309: =(B309/B310)-1 -> 0.012151215 | E309: 45463 | F309: 5244.13 | G309: =(F309/F310)-1 -> 0.016032534 | J309: =(B310/B311)-1 -> -0.0084783579 | K309: =(F310/F311)-1 -> 0.0085134071
A310: 45462 | B310: 222.2 | C310: =(B310/B311)-1 -> -0.0084783579 | E310: 45462 | F310: 5161.38 | G310: =(F310/F311)-1 -> 0.0085134071 | J310: =(B311/B312)-1 -> 0.0049327354 | K310: =(F311/F312)-1 -> 0.0068087032
A311: 45456 | B311: 224.1 | C311: =(B311/B312)-1 -> 0.0049327354 | E311: 45456 | F311: 5117.81 | G311: =(F311/F312)-1 -> 0.0068087032 | J311: =(B312/B313)-1 -> -0.0022371365 | K311: =(F312/F313)-1 -> 0.0025995953
A312: 45455 | B312: 223 | C312: =(B312/B313)-1 -> -0.0022371365 | E312: 45455 | F312: 5083.2 | G312: =(F312/F313)-1 -> 0.0025995953 | J312: =(B313/B314)-1 -> -0.0084294587 | K312: =(F313/F314)-1 -> -0.0070252199
A313: 45454 | B313: 223.5 | C313: =(B313/B314)-1 -> -0.0084294587 | E313: 45454 | F313: 5070.02 | G313: =(F313/F314)-1 -> -0.0070252199 | J313: =(B314/B315)-1 -> -0.0096660808 | K313: =(F314/F315)-1 -> -0.025094896
... A1188: 43433 | B1188: 362.7 | C1188: =(B1188/B1189)-1 -> -0.012792597 | E1188: 43433 | F1188: 5281.25 | G1188: =(F1188/F1189)-1 -> -0.001034668 | J1188: =(B1189/B1190)-1 -> 0.0038251366 | K1188: =(F1189/F1190)-1 -> -0.00034414035
A1189: 43432 | B1189: 367.4 | C1189: =(B1189/B1190)-1 -> 0.0038251366 | E1189: 43432 | F1189: 5286.72 | G1189: =(F1189/F1190)-1 -> -0.00034414035
A1190: 43431 | B1190: 366 | E1190: 43431 | F1190: 5288.54

Sheet CAPM
A1: Using DSEX/DGEN | F1: Using Market Capitalization | Q1: Step 01: Over here, I took 20 years worth of ending price from DSEX Index (Investing.com). Discrete return method has been used to find the changes through the years. To adjust for the final average of all these rates, the return rates were added with 1 (Geomean function will be used for averaging these rates).
A2: Year | B2: Index | C2: Return | F2: Year | G2: Market cap (Tk Crore) | H2: Return | I2: GEO Mean Adjusted
A3: 2005 | B3: 1630.91 | F3: 2005 | G3: 222000
A4: 2006 | B4: 1564.94 | C4: =(B4/B3)-1 -> -0.04044981 | D4: =C4+1 -> 0.95955019 | F4: 2006 | G4: 323368 | H4: =(G4/G3)-1 -> 0.45661261 | I4: =H4+1 -> 1.4566126
A5: 2007 | B5: 2933.67 | C5: =(B5/B4)-1 -> 0.87462139 | D5: =C5+1 -> 1.8746214 | F5: 2007 | G5: 753955 | H5: =(G5/G4)-1 -> 1.3315696 | I5: =H5+1 -> 2.3315696 | L5: Cost of Equity (via CAPM) | Q5: Step 02:As BD market is very volatile, hence market cap data will be used for 20 years. The data has been collected from BSEC Annual reports over the years. The same step repeated as step 1, just average of 20 years and 10 years data has been taken to keep consistency.
A6: 2008 | B6: 2717.94 | C6: =(B6/B5)-1 -> -0.073535878 | D6: =C6+1 -> 0.92646412 | F6: 2008 | G6: 1059530 | H6: =(G6/G5)-1 -> 0.40529607 | I6: =H6+1 -> 1.4052961 | L6: Market Return (Rm) | N6: =M14 -> 0.14200259
A7: 2009 | B7: 4409.94 | C7: =(B7/B6)-1 -> 0.6225303 | D7: =C7+1 -> 1.6225303 | F7: 2009 | G7: 1887177 | H7: =(G7/G6)-1 -> 0.78114541 | I7: =H7+1 -> 1.7811454 | L7: Risk free rate (Rf) | N7: =(0.09689+0.12)/2 -> 0.108445
A8: 2010 | B8: 8060.85 | C8: =(B8/B7)-1 -> 0.82788201 | D8: =C8+1 -> 1.827882 | F8: 2010 | G8: 3471109 | H8: =(G8/G7)-1 -> 0.8393129 | I8: =H8+1 -> 1.8393129 | L8: GP Beta | N8: ='[2]Return (Daily)'!N5 -> 0.85102811
A9: 2011 | B9: 5112.03 | C9: =(B9/B8)-1 -> -0.36581998 | D9: =C9+1 -> 0.63418002 | F9: 2011 | G9: 2327000 | H9: =(G9/G8)-1 -> -0.32960907 | I9: =H9+1 -> 0.67039093 | L9: CAPM (Ra) | N9: =N7+N8*(N6-N7) -> 0.13700346
A10: 2012 | B10: 4102.48 | C10: =(B10/B9)-1 -> -0.19748515 | D10: =C10+1 -> 0.80251485 | F10: 2012 | G10: 1933500 | H10: =(G10/G9)-1 -> -0.16910185 | I10: =H10+1 -> 0.83089815
A11: 2013 | B11: 4266.55 | C11: =(B11/B10)-1 -> 0.039992882 | D11: =C11+1 -> 1.0399929 | F11: 2013 | G11: 1977400 | H11: =(G11/G10)-1 -> 0.022704939 | I11: =H11+1 -> 1.0227049 | K11: Using DSEX Market capitalization data of 20 years (2005-2025) | Q11: Step 03: Over here, the market average has been found using Geomean function for 20 years of market cap data. The market return (Rm) is equal to the market cap average.
A12: 2014 | B12: 4864.96 | C12: =(B12/B11)-1 -> 0.14025618 | D12: =C12+1 -> 1.1402562 | F12: 2014 | G12: 2694448 | H12: =(G12/G11)-1 -> 0.36262162 | I12: =H12+1 -> 1.3626216 | K12: Market Return, Rm (whole period) | M12: =GEOMEAN(I3:I23)-1 -> 0.18549203
A13: 2015 | B13: 4629.64 | C13: =(B13/B12)-1 -> -0.048370387 | D13: =C13+1 -> 0.95162961 | F13: 2015 | G13: 2607793 | H13: =(G13/G12)-1 -> -0.032160576 | I13: =H13+1 -> 0.96783942 | K13: Market cap (last 10 years) | M13: =GEOMEAN(I14:I23)-1 -> 0.098513157
A14: 2016 | B14: 5036.05 | C14: =(B14/B13)-1 -> 0.087784363 | D14: =C14+1 -> 1.0877844 | F14: 2016 | G14: 3186000 | H14: =(G14/G13)-1 -> 0.22172274 | I14: =H14+1 -> 1.2217227 | K14: Average Rm | M14: =AVERAGE(M12,M13) -> 0.14200259
A15: 2017 | B15: 6244.52 | C15: =(B15/B14)-1 -> 0.23996386 | D15: =C15+1 -> 1.2399639 | F15: 2017 | G15: 3801000 | H15: =(G15/G14)-1 -> 0.19303202 | I15: =H15+1 -> 1.193032
A16: 2018 | B16: 5385.64 | C16: =(B16/B15)-1 -> -0.1375414 | D16: =C16+1 -> 0.8624586 | F16: 2018 | G16: 3847000 | H16: =(G16/G15)-1 -> 0.012102078 | I16: =H16+1 -> 1.0121021
A17: 2019 | B17: 4452.93 | C17: =(B17/B16)-1 -> -0.17318462 | D17: =C17+1 -> 0.82681538 | F17: 2019 | G17: 3998000 | H17: =(G17/G16)-1 -> 0.039251365 | I17: =H17+1 -> 1.0392514 | Q17: Step 4: Bangladesh Bank treasury bond data for 364 days is 9.69% to 12% which is the Rf rate. With the other information available, the cost of equity using the CAPM method has been found.
A18: 2020 | B18: 5402.07 | C18: =(B18/B17)-1 -> 0.21314954 | D18: =C18+1 -> 1.2131495 | F18: 2020 | G18: 3120000 | H18: =(G18/G17)-1 -> -0.2196098 | I18: =H18+1 -> 0.7803902
A19: 2021 | B19: 6756.66 | C19: =(B19/B18)-1 -> 0.25075388 | D19: =C19+1 -> 1.2507539 | F19: 2021 | G19: 5142800 | H19: =(G19/G18)-1 -> 0.64833333 | I19: =H19+1 -> 1.6483333
A20: 2022 | B20: 6206.81 | C20: =(B20/B19)-1 -> -0.081378965 | D20: =C20+1 -> 0.91862103 | F20: 2022 | G20: 5177816 | H20: =(G20/G19)-1 -> 0.0068087423 | I20: =H20+1 -> 1.0068087
A21: 2023 | B21: 6246.5 | C21: =(B21/B20)-1 -> 0.0063945892 | D21: =C21+1 -> 1.0063946 | F21: 2023 | G21: 7720780 | H21: =(G21/G20)-1 -> 0.49112676 | I21: =H21+1 -> 1.4911268
A22: 2024 | B22: 5216.44 | C22: =(B22/B21)-1 -> -0.16490195 | D22: =C22+1 -> 0.83509805 | F22: 2024 | G22: 6621673 | H22: =(G22/G21)-1 -> -0.14235699 | I22: =H22+1 -> 0.85764301
A23: 2025 | B23: 4914.72 | C23: =(B23/B22)-1 -> -0.057840213 | D23: =C23+1 -> 0.94215979 | F23: 2025 | G23: 6673071 | H23: =(G23/G22)-1 -> 0.0077620867 | I23: =H23+1 -> 1.0077621
A27: Using DSEX Index data of 20 years (2005-2025)
A28: Market Return (Rm) | C28: =GEOMEAN(D4:D23)-1 -> 0.056704214

Sheet Cost of Equity
A1: Cost of Equity using the Gordon Growth Model
A2: Year | B2: Cash Dividend | C2: Growth Rate
A3: 2018 | B3: 30381750
A4: 2019 | B4: 26301675 | C4: =(B4/B3)-1 -> -0.13429361
A5: 2020 | B5: 28110077 | C5: =(B5/B4)-1 -> 0.068756153
A6: 2021 | B6: 33058662 | C6: =(B6/B5)-1 -> 0.1760431
A7: 2022 | B7: 33584032 | C7: =(B7/B6)-1 -> 0.015892053
A8: 2023 | B8: 9093155 | C8: =(B8/B7)-1 -> -0.72924171
A9: 2024 | B9: 42317213 | C9: =(B9/B8)-1 -> 3.6537437
A11: CAGR (g) | B11: =((B9/B3)^(1/7))-1 -> 0.048474212
A12: Current Market price (P0) | B12: 279
A13: Dividend of last year (2024_D0) | B13: 33
A14: Current Year Dividend (2025_D1) | B14: =B13*(1+B11) -> 34.599649
A15: Ke | B15: =(B14/B12)+B11 -> 0.17248729
A21: 1. Total cash dividends fpr 7 years were used to find the Compunded Annual Growth Rate (CAGR).
A22: 2. Similarily, 6 years data has been used to calculate the Sustainable Growth Rate (SGR) to observe an alternative g rate
A23: 3. CAGR is a better method of growth rate (compounding factor)
A24: 4. Latest market price has been taken (4th Dec, 2025)
A25: 5. Dividend per share for 2024 has been taken from the Annual Report of GP 2024
A26: 6. All the information was then plugged in the DDM formula.

Sheet Cost of Debt
A1: Year | B1: 2025 | C1: 2024 | D1: 2023 | E1: 2022 | F1: 2021 | G1: 2020 | H1: 2019
A2: Cash & Cash Equivalents | B2: 15706467000 | C2: 7334432000 | D2: 16718338000 | E2: 3325922000 | F2: 2748661000 | G2: 2598738000 | H2: 13760677000
A4: Loans & Borrowings | B4: 0 | C4: 5000000000 | D4: 3119599000 | E4: 5037394000 | F4: 5500000000 | G4: 1240000000 | H4: 2934284000
A5: Lease Liabilities | B5: =48233913000+10925359000 -> 59159272000 | C5: =48853886000+11112469000 -> 59966355000 | D5: =40212825000+10006247000 -> 50219072000 | E5: =41046666000+10852496000 -> 51899162000 | F5: =22675135000+9445609000 -> 32120744000 | G5: =14146840000+6328697000 -> 20475537000 | H5: =13484106000+7349549000 -> 20833655000
A7: Net Debt | B7: =SUM(B4:B5)-B2 -> 43452805000 | C7: =SUM(C4:C5)-SUM(C2:C2) -> 57631923000 | D7: =SUM(D4:D5)-SUM(D2:D2) -> 36620333000 | E7: =SUM(E4:E5)-SUM(E2:E2) -> 53610634000 | F7: =SUM(F4:F5)-SUM(F2:F2) -> 34872083000 | G7: =SUM(G4:G5)-SUM(G2:G2) -> 19116799000 | H7: =SUM(H4:H5)-SUM(H2:H2) -> 10007262000
A10: Interest Expense | B10: 53214000 | C10: 451408000 | D10: 668820000 | E10: 156852000 | F10: 87206000 | G10: 1245125000 | H10: 804706000
A11: Lease Interest | B11: 1418588000 | C11: 4949207000 | D11: 4706978000 | E11: 3254319000 | F11: 2495806000 | G11: 1803873000 | H11: 2121092000
A12: Interest Income | B12: 168926000 | C12: 715732000 | D12: 352911000 | E12: 456720000 | F12: 147881000 | G12: 376627000 | H12: 597542000
A14: Net Interest Expense | B14: =SUM(B10:B11)-B12 -> 1302876000 | C14: =SUM(C10:C11)-C12 -> 4684883000 | D14: =SUM(D10:D11)-D12 -> 5022887000 | E14: =SUM(E10:E11)-E12 -> 2954451000 | F14: =SUM(F10:F11)-F12 -> 2435131000 | G14: =SUM(G10:G11)-G12 -> 2672371000 | H14: =SUM(H10:H11)-H12 -> 2328256000
A17: Income before Tax | B17: 11005978000 | C17: 53543224000 | D17: 54323873000 | E17: 30091598000 | F17: 34129056000 | G17: 37187037000 | H17: 34516760000
A18: Income Tax Expense | B18: 4666667000 | C18: 17234497000 | D18: 21249000000 | E18: 21898505000 | F18: 26691690000 | G18: 25613869000 | H18: 29382199000
A20: Tax Rate | B20: =B18/B17 -> 0.42401202 | C20: =C18/C17 -> 0.32188008 | D20: =D18/D17 -> 0.391154 | E20: =E18/E17 -> 0.72772822 | F20: =F18/F17 -> 0.78208111 | G20: =G18/G17 -> 0.68878488 | H20: =H18/H17 -> 0.85124441
A23: Lease liabilities are included in net debt because, under IFRS 16, long term leases are treated like interest-bearing financing, not just operating costs. Grameenphone pays regular finance charges on these obligations so they are similar to loans and directly contribute to the true cost of debt capital.
A28: Year | B28: Net Debt | C28: Average Net Debt | D28: Net Interest | E28: Pre-tax Cost of Debt
A29: 2019 | B29: 10007262000 | D29: 2328256000
A30: 2020 | B30: 19116799000 | C30: =AVERAGE(B29,B30) -> 14562030500 | D30: 2672371000 | E30: =D30/C30 -> 0.18351637
A31: 2021 | B31: 34872083000 | C31: =AVERAGE(B30,B31) -> 26994441000 | D31: 2435131000 | E31: =D31/C31 -> 0.09020861
A32: 2022 | B32: 53610634000 | C32: =AVERAGE(B31,B32) -> 44241358500 | D32: 2954451000 | E32: =D32/C32 -> 0.066780296
A33: 2023 | B33: 36620333000 | C33: =AVERAGE(B32,B33) -> 45115483500 | D33: 5022887000 | E33: =D33/C33 -> 0.11133399
A34: 2024 | B34: 57631923000 | C34: =AVERAGE(B33,B34) -> 47126128000 | D34: 4684883000 | E34: =D34/C34 -> 0.099411583
A35: 2025 | B35: 43452805000 | C35: =AVERAGE(B34,B35) -> 50542364000 | D35: 1302876000 | E35: =D35/C35 -> 0.0257779
C36: =SUM(C30:C35) -> 228581805500 | D36: =SUM(D30:D35) -> 19072599000 | E36: =D36/C36 -> 0.083438833
A39: The 8.34% is the historical rate which shows what Grameenphone effectively paid on its debt over the years of 2020 to 2025.
A44: Year | B44: Tax Rates | E44: Market Cost of Debt (pre-tax) | F44: 0.1244
A45: 2019 | B45: 0.85124441 | E45: Cost of Debt | F45: =F44*(1-B52) -> 0.049993077
A46: 2020 | B46: 0.68878488
A47: 2021 | B47: 0.78208111
A48: 2022 | B48: 0.72772822
A49: 2023 | B49: 0.391154
A50: 2024 | B50: 0.32188008
A51: 2025 | B51: 0.42401202
B52: =AVERAGE(B45:B51) -> 0.59812639
A54: Statutory Tax Rate | B54: 0.4

Sheet WACC
A1: Cost of Equity | B1: =[2]CAPM!M14 -> 0.14200259
A3: After-tax Cost of Debt | B3: ='[2]Debt Calculations'!F47 -> 0.049993077
A5: EQUITY:
A6: Share Price | B6: 278.4
A7: Number of Shares Outstanding | B7: 1350300022
A9: DEBT:
A10: Year | B10: 2025 | C10: 2024 | D10: 2023 | E10: 2022 | F10: 2021 | G10: 2020 | H10: 2019
A11: Loans & Borrowings | B11: 0 | C11: 5000000000 | D11: 3119599000 | E11: 5037394000 | F11: 5500000000 | G11: 1240000000 | H11: 2934284000
A12: Lease Liabilities | B12: 59159272000 | C12: 59966355000 | D12: 50219072000 | E12: 51899162000 | F12: 32120744000 | G12: 20475537000 | H12: 20833655000
A13: Total Debt | B13: =B11+B12 -> 59159272000 | C13: =C11+C12 -> 64966355000 | D13: =D11+D12 -> 53338671000 | E13: =E11+E12 -> 56936556000 | F13: =F11+F12 -> 37620744000 | G13: =G11+G12 -> 21715537000 | H13: =H11+H12 -> 23767939000
A15: Market Value of Debt | B15: =AVERAGE(B13:H13) -> 4.5357868e+10
A16: Market Value of Equity | B16: =B7*B6 -> 3.7592353e+11
A17: WACC | B17: =(B16/(B16+B15)*B1)+(B15/(B15+B16)*B3) -> 0.13209626

Sheet Income Statement
A1: Income Statement [Historical] | J1: Income Statement [Common Sized]
A2: Particulars | B2: 2019 | C2: 2020 | D2: 2021 | E2: 2022 | F2: 2023 | G2: 2024 | J2: Particulars | K2: 2019 | L2: 2020 | M2: 2021 | N2: 2022 | O2: 2023 | P2: 2024
A3: Revenue | B3: 143656271 | C3: 139606161 | D3: 143065872 | E3: 150403469 | F3: 158715818 | G3: 158447003 | J3: Revenue | K3: 1 | L3: 1 | M3: 1 | N3: 1 | O3: 1 | P3: 1
A4: Cost of material and traffic charges | B4: -8465283 | C4: -8812905 | D4: -9604705 | E4: -10088492 | F4: -9961041 | G4: -9825692 | J4: Cost of material and traffic charges | K4: ='Income Statement'!K4/'Income Statement'!$B$3*-1 -> 0.058927347 | L4: ='Income Statement'!L4/'Income Statement'!$C$3*-1 -> 0.063126906 | M4: ='Income Statement'!M4/'Income Statement'!$D$3*-1 -> 0.067134844 | N4: ='Income Statement'!N4/'Income Statement'!$E$3*-1 -> 0.067076192 | O4: ='Income Statement'!O4/'Income Statement'!$F$3*-1 -> 0.062760228 | P4: ='Income Statement'!P4/'Income Statement'!$G$3*-1 -> 0.062012482
A5: Revenue sharing, spectrum charges and licence fees | B5: -10107313 | C5: -10478334 | D5: -10895286 | E5: -12583383 | F5: -12009842 | G5: -12068041 | J5: Revenue sharing, spectrum charges and licence fees | K5: ='Income Statement'!K5/'Income Statement'!$B$3*-1 -> 0.070357618 | L5: ='Income Statement'!L5/'Income Statement'!$C$3*-1 -> 0.075056387 | M5: ='Income Statement'!M5/'Income Statement'!$D$3*-1 -> 0.076155731 | N5: ='Income Statement'!N5/'Income Statement'!$E$3*-1 -> 0.083664181 | O5: ='Income Statement'!O5/'Income Statement'!$F$3*-1 -> 0.075668841 | P5: ='Income Statement'!P5/'Income Statement'!$G$3*-1 -> 0.076164527
A6: Gross Profit | B6: =B3+B4+B5 -> 125083675 | C6: =C3+C4+C5 -> 120314922 | D6: =D3+D4+D5 -> 122565881 | E6: =E3+E4+E5 -> 127731594 | F6: =F3+F4+F5 -> 136744935 | G6: =G3+G4+G5 -> 136553270 | J6: Gross Profit | K6: ='Income Statement'!K6/'Income Statement'!$B$3 -> 0.87071503 | L6: ='Income Statement'!L6/'Income Statement'!$C$3 -> 0.86181671 | M6: ='Income Statement'!M6/'Income Statement'!$D$3 -> 0.85670943 | N6: ='Income Statement'!N6/'Income Statement'!$E$3 -> 0.84925963 | O6: ='Income Statement'!O6/'Income Statement'!$F$3 -> 0.86157093 | P6: ='Income Statement'!P6/'Income Statement'!$G$3 -> 0.86182299
A7: Salaries and personnel cost | B7: -9437578 | C7: -10027226 | D7: -11507572 | E7: -9235728 | F7: -8494009 | G7: -8517867 | J7: Salaries and personnel cost | K7: ='Income Statement'!K7/'Income Statement'!$B$3*-1 -> 0.065695552 | L7: ='Income Statement'!L7/'Income Statement'!$C$3*-1 -> 0.071825097 | M7: ='Income Statement'!M7/'Income Statement'!$D$3*-1 -> 0.080435479 | N7: ='Income Statement'!N7/'Income Statement'!$E$3*-1 -> 0.06140635 | O7: ='Income Statement'!O7/'Income Statement'!$F$3*-1 -> 0.053517092 | P7: ='Income Statement'!P7/'Income Statement'!$G$3*-1 -> 0.053758461
A8: Operation and maintenance | B8: -5898863 | C8: -4984745 | D8: -5550948 | E8: -4252580 | F8: -6272385 | G8: -6942686 | J8: Operation and maintenance | K8: ='Income Statement'!K8/'Income Statement'!$B$3*-1 -> 0.041062342 | L8: ='Income Statement'!L8/'Income Statement'!$C$3*-1 -> 0.035705767 | M8: ='Income Statement'!M8/'Income Statement'!$D$3*-1 -> 0.038799945 | N8: ='Income Statement'!N8/'Income Statement'!$E$3*-1 -> 0.028274481 | O8: ='Income Statement'!O8/'Income Statement'!$F$3*-1 -> 0.039519596 | P8: ='Income Statement'!P8/'Income Statement'!$G$3*-1 -> 0.043817086
A9: Sales, marketing and commissions | B9: -13480018 | C9: -11771112 | D9: -13341089 | E9: -15278933 | F9: -15428172 | G9: -16247666 | J9: Sales, marketing and commissions | K9: ='Income Statement'!K9/'Income Statement'!$B$3*-1 -> 0.093835221 | L9: ='Income Statement'!L9/'Income Statement'!$C$3*-1 -> 0.084316565 | M9: ='Income Statement'!M9/'Income Statement'!$D$3*-1 -> 0.093251373 | N9: ='Income Statement'!N9/'Income Statement'!$E$3*-1 -> 0.10158631 | O9: ='Income Statement'!O9/'Income Statement'!$F$3*-1 -> 0.097206266 | P9: ='Income Statement'!P9/'Income Statement'!$G$3*-1 -> 0.10254322
A10: Depreciation and amortisation | B10: -23451039 | C10: -23649950 | D10: -23016177 | E10: -27899584 | F10: -32321703 | G10: -34551840 | J10: Depreciation and amortisation | K10: ='Income Statement'!K10/'Income Statement'!$B$3*-1 -> 0.1632441 | L10: ='Income Statement'!L10/'Income Statement'!$C$3*-1 -> 0.16940477 | M10: ='Income Statement'!M10/'Income Statement'!$D$3*-1 -> 0.16087818 | N10: ='Income Statement'!N10/'Income Statement'!$E$3*-1 -> 0.18549827 | O10: ='Income Statement'!O10/'Income Statement'!$F$3*-1 -> 0.20364513 | P10: ='Income Statement'!P10/'Income Statement'!$G$3*-1 -> 0.2180656
A11: Operating Profit | B11: =B6+B7+B8+B9+B10 -> 72816177 | C11: =C6+C7+C8+C9+C10 -> 69881889 | D11: =D6+D7+D8+D9+D10 -> 69150095 | E11: =E6+E7+E8+E9+E10 -> 71064769 | F11: =F6+F7+F8+F9+F10 -> 74228666 | G11: 59129211 | J11: Operating Profit | K11: ='Income Statement'!K11/'Income Statement'!$B$3 -> 0.50687782 | L11: ='Income Statement'!L11/'Income Statement'!$C$3 -> 0.50056451 | M11: ='Income Statement'!M11/'Income Statement'!$D$3 -> 0.48334445 | N11: ='Income Statement'!N11/'Income Statement'!$E$3 -> 0.47249421 | O11: ='Income Statement'!O11/'Income Statement'!$F$3 -> 0.46768285 | P11: ='Income Statement'!P11/'Income Statement'!$G$3 -> 0.37317974
A12: Other operating (expenses)/income | B12: -6164349 | C12: -6442284 | D12: -5814523 | E12: -7466582 | F12: -9799694 | G12: -11164000 | J12: Other operating (expenses)/income | K12: ='Income Statement'!K12/'Income Statement'!$B$3*-1 -> 0.042910407 | L12: ='Income Statement'!L12/'Income Statement'!$C$3*-1 -> 0.04614613 | M12: ='Income Statement'!M12/'Income Statement'!$D$3*-1 -> 0.040642278 | N12: ='Income Statement'!N12/'Income Statement'!$E$3*-1 -> 0.049643682 | O12: ='Income Statement'!O12/'Income Statement'!$F$3*-1 -> 0.061743651 | P12: ='Income Statement'!P12/'Income Statement'!$G$3*-1 -> 0.07045889
A13: Finance (expense)/income | B13: -2523060 | C13: -376473 | D13: -2595396 | E13: -10177407 | F13: -9383833 | G13: -4986593 | J13: Finance (expense)/income | K13: ='Income Statement'!K13/'Income Statement'!$B$3*-1 -> 0.017563173 | L13: ='Income Statement'!L13/'Income Statement'!$C$3*-1 -> 0.002696679 | M13: ='Income Statement'!M13/'Income Statement'!$D$3*-1 -> 0.018141266 | N13: ='Income Statement'!N13/'Income Statement'!$E$3*-1 -> 0.067667369 | O13: ='Income Statement'!O13/'Income Statement'!$F$3*-1 -> 0.05912349 | P13: ='Income Statement'!P13/'Income Statement'!$G$3*-1 -> 0.031471678
A14: Foreign exchange (loss)/gain | B14: -229809 | C14: -262226 | D14: 80570 | E14: -1430677 | F14: -721266 | G14: -599394 | J14: Foreign exchange (loss)/gain | K14: ='Income Statement'!K14/'Income Statement'!$B$3*-1 -> 0.0015997144 | L14: ='Income Statement'!L14/'Income Statement'!$C$3*-1 -> 0.0018783268 | M14: ='Income Statement'!M14/'Income Statement'!$D$3 -> 0.00056316715 | N14: ='Income Statement'!N14/'Income Statement'!$E$3*-1 -> 0.0095122607 | O14: ='Income Statement'!O14/'Income Statement'!$F$3*-1 -> 0.0045443864 | P14: ='Income Statement'!P14/'Income Statement'!$G$3*-1 -> 0.0037829305
A15: Profit before tax | B15: =B11+B12+B13+B14 -> 63898959 | C15: =C11+C12+C13+C14 -> 62800906 | D15: =D11+D12+D13+D14 -> 60820746 | E15: =E11+E12+E13+E14 -> 51990103 | F15: =F11+F12+F13+F14 -> 54323873 | G15: =G11+G12+G13+G14 -> 42379224 | J15: Profit before tax | K15: ='Income Statement'!K15/'Income Statement'!$B$3 -> 0.44480452 | L15: ='Income Statement'!L15/'Income Statement'!$C$3 -> 0.44984337 | M15: ='Income Statement'!M15/'Income Statement'!$D$3 -> 0.42512407 | N15: ='Income Statement'!N15/'Income Statement'!$E$3 -> 0.3456709 | O15: ='Income Statement'!O15/'Income Statement'!$F$3 -> 0.34227132 | P15: ='Income Statement'!P15/'Income Statement'!$G$3 -> 0.26746624
A16: Income tax expense | B16: -29382199 | C16: -25613869 | D16: -26691690 | E16: -21898505 | F16: -21249000 | G16: -17234497 | J16: Income tax expense | K16: ='Income Statement'!K16/'Income Statement'!$B$3*-1 -> 0.20453127 | L16: ='Income Statement'!L16/'Income Statement'!$C$3*-1 -> 0.18347234 | M16: ='Income Statement'!M16/'Income Statement'!$D$3*-1 -> 0.18656923 | N16: ='Income Statement'!N16/'Income Statement'!$E$3*-1 -> 0.1455984 | O16: ='Income Statement'!O16/'Income Statement'!$F$3*-1 -> 0.1338808 | P16: ='Income Statement'!P16/'Income Statement'!$G$3*-1 -> 0.10877137
A17: Profit after tax | B17: =B15+B16 -> 34516760 | C17: =C15+C16 -> 37187037 | D17: =D15+D16 -> 34129056 | E17: =E15+E16 -> 30091598 | F17: =F15+F16 -> 33074873 | G17: =G15+G16 -> 25144727 | J17: Profit after tax | K17: ='Income Statement'!K17/'Income Statement'!$B$3 -> 0.24027326 | L17: ='Income Statement'!L17/'Income Statement'!$C$3 -> 0.26637103 | M17: ='Income Statement'!M17/'Income Statement'!$D$3 -> 0.23855484 | N17: ='Income Statement'!N17/'Income Statement'!$E$3 -> 0.2000725 | O17: ='Income Statement'!O17/'Income Statement'!$F$3 -> 0.20839053 | P17: ='Income Statement'!P17/'Income Statement'!$G$3 -> 0.15869487
A18: Other comprehensive income | J18: Other comprehensive income
A19: Item that will not be reclassified subsequently to profit or loss | J19: Item that will not be reclassified subsequently to profit or loss
A20: Remeasurement of defined benefit plan | B20: 127659 | C20: -783080 | D20: 166647 | E20: -3164 | F20: 386265 | G20: 379566 | J20: Remeasurement of defined benefit plan | K20: ='Income Statement'!K20/'Income Statement'!$B$3 -> 0.00088864203 | L20: ='Income Statement'!L20/'Income Statement'!$C$3*-1 -> 0.005609208 | M20: ='Income Statement'!M20/'Income Statement'!$D$3 -> 0.0011648271 | N20: ='Income Statement'!N20/'Income Statement'!$E$3 -> -2.1036749e-05 | O20: ='Income Statement'!O20/'Income Statement'!$F$3 -> 0.0024336894 | P20: ='Income Statement'!P20/'Income Statement'!$G$3 -> 0.0023955392
A21: Related taxes | B21: -51063 | C21: 313232 | D21: -66659 | E21: 1266 | F21: -154506 | G21: -151826 | J21: Related taxes | K21: ='Income Statement'!K21/'Income Statement'!$B$3*-1 -> 0.00035545263 | L21: ='Income Statement'!L21/'Income Statement'!$C$3 -> 0.0022436832 | M21: ='Income Statement'!M21/'Income Statement'!$D$3*-1 -> 0.00046593222 | N21: ='Income Statement'!N21/'Income Statement'!$E$3 -> 8.417359e-06 | O21: ='Income Statement'!O21/'Income Statement'!$F$3*-1 -> 0.00097347575 | P21: ='Income Statement'!P21/'Income Statement'!$G$3*-1 -> 0.00095821314
A22: Total comprehensive income for the year | B22: =B17+B20+B21 -> 34593356 | C22: =C17+C20-C21 -> 36090725 | D22: =D17-D20+D21 -> 33895750 | E22: =E17+E20-E21 -> 30087168 | F22: =F17-F20+F21 -> 32534102 | G22: =G17-G20+G21 -> 24613335 | J22: Total comprehensive income for the year | K22: ='Income Statement'!K22/'Income Statement'!$B$3 -> 0.24080645 | L22: ='Income Statement'!L22/'Income Statement'!$C$3 -> 0.25851814 | M22: ='Income Statement'!M22/'Income Statement'!$D$3 -> 0.23692408 | N22: ='Income Statement'!N22/'Income Statement'!$E$3 -> 0.20004305 | O22: ='Income Statement'!O22/'Income Statement'!$F$3 -> 0.20498336 | P22: ='Income Statement'!P22/'Income Statement'!$G$3 -> 0.15534112
A23: Earnings per share
A24: Basic earnings per share
A25: (per value BDT 10 each in BDT) | B25: 25.56 | C25: 27.54 | D25: 25.28 | E25: 22.29 | F25: 24.49 | G25: 26.89

Sheet Balance Sheet
A1: Balance Sheet [Historical] | I1: Balance Sheet [Common Sized]
A2: Particulars | B2: 2019 | C2: 2020 | D2: 2021 | E2: 2022 | F2: 2023 | G2: 2024 | I2: Particulars | J2: 2019 | K2: 2020 | L2: 2021 | M2: 2022 | N2: 2023 | O2: 2024
A3: Assets | I3: Assets
A4: Non-current assets | I4: Non-current assets
A5: Property, plant and equipment | B5: 62,396,558 | C5: 56901192 | D5: 60,387,950 | E5: 62849119 | F5: 67019995 | G5: 68,335,441 | I5: Property, plant and equipment | J5: 0.41951659 | K5: 0.3839893 | L5: 0.37046304 | M5: 0.33956452 | N5: 0.33439739 | O5: 0.34364763
A6: Intangible assets | B6: 2,274,803 | C6: 2316587 | D6: 3,632,296 | E6: 4023092 | F6: 4396001 | G6: 4,774,439 | I6: Intangible assets | J6: 0.015294395 | K6: 0.015633146 | L6: 0.022283111 | M6: 0.021736172 | N6: 0.021933921 | O6: 0.024009864
A7: Right-of-use assets | B7: 58,028,533 | C7: 53532673 | D7: 62,533,832 | E7: 80501010 | F7: 76086723 | G7: 77,710,892 | I7: Right-of-use assets | J7: 0.39014864 | K7: 0.36125735 | L7: 0.38362742 | M7: 0.43493508 | N7: 0.37963598 | O7: 0.39079523
A8: Contract cost | B8: 4,480,157 | C8: 4934438 | D8: 6,035,958 | E8: 5148908 | F8: 7141432 | G8: 10,436,997 | I8: Contract cost | J8: 0.030121857 | K8: 0.033299327 | L8: 0.0370289 | M8: 0.02781879 | N8: 0.035632295 | O8: 0.052485932
A9: Other non-current assets | B9: 555,200 | C9: 20568456 | D9: 20,549,067 | E9: 20471567 | F9: 20471568 | G9: 1,458,619 | I9: Other non-current assets | J9: 0.0037328279 | K9: 0.13880319 | L9: 0.12606273 | M9: 0.11060486 | N9: 0.10214323 | O9: 0.0073351538
A10: Total non-current assets | B10: 127,735,251 | C10: 138,253,346 | D10: 153,139,103 | E10: 172993696 | F10: 175115719 | G10: 20,526,814 | I10: Total non-current assets | J10: 0.85881432 | K10: 0.93298231 | L10: 0.9394652 | M10: 0.93465942 | N10: 0.87374283 | O10: 0.10322595
A11: Current assets | I11: Current assets
A12: Inventories | B12: 225,441 | C12: 201068 | D12: 260,230 | E12: 1088393 | F12: 591449 | G12: 407655 | I12: Inventories | J12: 0.0015157285 | K12: 0.0013568777 | L12: 0.0015964376 | M12: 0.0058804268 | N12: 0.0029510447 | O12: 0.0020500296
A13: Trade receivables and others | B13: 7,013,053 | C13: 7131165 | D13: 6,858,686 | E13: 7679405 | F13: 7994702 | G13: 7,867,938 | I13: Trade receivables and others | J13: 0.047151513 | K13: 0.048123615 | L13: 0.042076104 | M13: 0.041490692 | N13: 0.0398897 | O13: 0.039566559
A14: Cash and cash equivalents | B14: 13,760,677 | C14: 2598738 | D14: 2,748,661 | E14: 3325922 | F14: 16718338 | G14: 7,334,432 | I14: Cash and cash equivalents | J14: 0.092518442 | K14: 0.0175372 | L14: 0.01686226 | M14: 0.017969466 | N14: 0.083416429 | O14: 0.036883646
A15: Total current assets | B15: 20,999,171 | C15: 9,930,971 | D15: 9,867,577 | E15: 12093720 | F15: 25304489 | G15: 15,610,025 | I15: Total current assets | J15: 0.14118568 | K15: 0.067017693 | L15: 0.060534801 | M15: 0.065340585 | N15: 0.12625717 | O15: 0.078500235
A16: Total assets | B16: 148,734,422 | C16: 148,184,317 | D16: 163,006,680 | E16: 185087416 | F16: 200420208 | G16: 198,853,227 | I16: Total assets | J16: 1 | K16: 1 | L16: 1 | M16: 1 | N16: 1 | O16: 1
A17: Equity and liabilities | I17: Equity and liabilities
A18: Shareholders’ equity | I18: Shareholders’ equity
A19: Share capital | B19: 13,503,000 | C19: 13503000 | D19: 13,503,000 | E19: 13503000 | F19: 13503000 | G19: 13503000 | I19: Share capital | J19: 0.090785978 | K19: 0.091123003 | L19: 0.082837096 | M19: 0.072954717 | N19: 0.067373446 | O19: 0.067904354
A20: Share premium | B20: 7,840,226 | C20: 7840226 | D20: 7,840,226 | E20: 7840226 | F20: 7840226 | G20: 7,840,226 | I20: Share premium | J20: 0.052712922 | K20: 0.052908608 | L20: 0.048097575 | M20: 0.042359584 | N20: 0.03911894 | O20: 0.0394272
A21: Capital reserve | B21: 14,446 | C21: 14446 | D21: 14,446 | E21: 14446 | F21: 14446 | G21: 14,446 | I21: Capital reserve | J21: 9.7126138e-05 | K21: 9.74867e-05 | L21: 8.8622135e-05 | M21: 7.8049607e-05 | N21: 7.207856e-05 | O21: 7.2646545e-05
A22: Deposit from shareholders | B22: 1,880 | I22: Deposit from shareholders | J22: 1.2639979e-05 | K22: 0 | L22: 0 | M22: 0 | N22: 0 | O22: 0
A23: Retained earnings | B23: 16,987,853 | C23: 30749942 | D23: 28,520,886 | E23: 24853086 | F23: 45331868 | G23: 43,384,785 | I23: Retained earnings | J23: 0.11421602 | K23: 0.20751145 | L23: 0.17496759 | M23: 0.13427756 | N23: 0.22618412 | O23: 0.21817491
A24: Total equity | B24: 38,347,405 | C24: 52,107,614 | D24: 49,878,558 | E24: 46210758 | F24: 66689540 | G24: 64,742,457 | I24: Total equity | J24: 0.25782468 | K24: 0.35164055 | L24: 0.30599088 | M24: 0.24966991 | N24: 0.33274858 | O24: 0.32557911
A25: Non-current liabilities | I25: Non-current liabilities
A26: Lease liabilities | B26: 13,484,106 | C26: 14146840 | D26: 22,675,135 | E26: 41046666 | F26: 40212825 | G26: 48,853,886 | I26: Lease liabilities | J26: 0.090658946 | K26: 0.095467862 | L26: 0.13910556 | M26: 0.22176908 | N26: 0.20064257 | O26: 0.24567812
A27: Deferred tax liabilities | B27: 5,216,029 | C27: 3350834 | D27: 3,425,488 | E27: 3060593 | F27: 479369 | G27: - | I27: Deferred tax liabilities | J27: 0.035069414 | K27: 0.022612609 | L27: 0.021014403 | M27: 0.016535932 | N27: 0.0023918197 | O27: -
A28: Employee benefits | B28: 936,703 | C28: 1641383 | D28: 1,336,085 | E28: 1340324 | F28: 384470 | G28: 395,836 | I28: Employee benefits | J28: 0.0062978226 | K28: 0.011076631 | L28: 0.0081965046 | M28: 0.0072415728 | N28: 0.0019183195 | O28: 0.0019905938
A29: Other non-current liabilities | B29: 323,957 | C29: 281272 | D29: 455,308 | E29: 496323 | F29: 456235 | G29: 546,133 | I29: Other non-current liabilities | J29: 0.0021780903 | K29: 0.0018981226 | L29: 0.0027931861 | M29: 0.0026815599 | N29: 0.0022763922 | O29: 0.0027464126
A30: Total non-current liabilities | B30: 19,960,795 | C30: 19,420,329 | D30: 27,892,016 | E30: 45943906 | F30: 41532899 | G30: 49,795,855 | I30: Total non-current liabilities | J30: 0.13420427 | K30: 0.13105522 | L30: 0.17110965 | M30: 0.24822815 | N30: 0.2072291 | O30: 0.25041512
A31: Current liabilities | I31: Current liabilities
A32: Trade payables and others | B32: 22,676,406 | C32: 23988115 | D32: 25,521,622 | E32: 27275330 | F32: 29619417 | G32: 28,366,808 | I32: Trade payables and others | J32: 0.15246239 | K32: 0.16188025 | L32: 0.15656795 | M32: 0.14736458 | N32: 0.14778658 | O32: 0.14265199
A33: Provisions | B33: 18,839,102 | C33: 14402559 | D33: 15,703,449 | E33: 23612398 | F33: 23946716 | G33: 24,920,485 | I33: Provisions | J33: 0.12666269 | K33: 0.097193544 | L33: 0.09633623 | M33: 0.1275743 | N33: 0.11948254 | O33: 0.125321
A34: Lease liabilities | B34: 7,349,549 | C34: 6328697 | D34: 9,445,609 | E34: 10852496 | F34: 10006247 | G34: 11,112,469 | I34: Lease liabilities | J34: 0.049413908 | K34: 0.042708278 | L34: 0.057946147 | M34: 0.058634435 | N34: 0.049926338 | O34: 0.055882769
A35: Loans and borrowings | B35: 2,934,284 | C35: 1240000 | D35: 5,500,000 | E35: 5037394 | F35: 3119599 | G35: 5,000,000 | I35: Loans and borrowings | J35: 0.019728345 | K35: 0.008367957 | L35: 0.033740949 | M35: 0.027216297 | N35: 0.015565292 | O35: 0.025144173
A36: Current tax liabilities | B36: 28,137,225 | C36: 24870650 | D36: 25,603,868 | E36: 23779920 | F36: 19459679 | G36: 12,769,919 | I36: Current tax liabilities | J36: 0.18917763 | K36: 0.16783591 | L36: 0.15707251 | M36: 0.1284794 | N36: 0.097094396 | O36: 0.064217811
A37: Other current liabilities | B37: 10,489,656 | C37: 5690023 | D37: 3,414,334 | E37: 2316342 | F37: 5968502 | G37: 2,077,180 | I37: Other current liabilities | J37: 0.070526082 | K37: 0.038398281 | L37: 0.020945976 | M37: 0.012514854 | N37: 0.029779941 | O37: 0.010445795
A38: Unclaimed Dividend | C38: 136330 | D38: 47,224 | E38: 58872 | F38: 77609 | G38: 68,054 | I38: Unclaimed Dividend | J38: 0 | K38: 0.00092000289 | L38: 0.00028970592 | M38: 0.00031807673 | N38: 0.00038723141 | O38: 0.00034223231
A39: Total current liabilities | B39: 90,426,222 | C39: 76,656,374 | D39: 85,236,106 | E39: 92932752 | F39: 92197769 | G39: 84,314,915 | I39: Total current liabilities | J39: 0.60797105 | K39: 0.51730423 | L39: 0.52289947 | M39: 0.50210195 | N39: 0.46002232 | O39: 0.42400577
A40: Total equity and liabilities | B40: 148,734,422 | C40: 148,184,317 | D40: 163,006,680 | E40: 185087416 | F40: 200420208 | G40: 198,853,227 | I40: Total equity and liabilities | J40: 1 | K40: 1 | L40: 1 | M40: 1 | N40: 1 | O40: 1

Sheet CAGR Based Sales forecast
A1: Year | B1: Cash Dividend | C1: Growth Rate | D1: CAGR (g) | E1: =((B8/B2)^(1/7))-1 -> 0.048474212
A2: 2018 | B2: 30381750 | D2: Current Market price (P0) | E2: 279
A3: 2019 | B3: 26301675 | C3: =(B3/B2)-1 -> -0.13429361 | D3: Dividend of last year (2024_D0) | E3: 33
A4: 2020 | B4: 28110077 | C4: =(B4/B3)-1 -> 0.068756153 | D4: Current Year Dividend (2025_D1) | E4: =E3*(1+E1) -> 34.599649
A5: 2021 | B5: 33058662 | C5: =(B5/B4)-1 -> 0.1760431
A6: 2022 | B6: 33584032 | C6: =(B6/B5)-1 -> 0.015892053
A7: 2023 | B7: 9093155 | C7: =(B7/B6)-1 -> -0.72924171
A8: 2024 | B8: 42317213 | C8: =(B8/B7)-1 -> 3.6537437
D11: Particulars | E11: 2019 | F11: 2020 | G11: 2021 | H11: 2022 | I11: 2023 | J11: 2024
D12: Revenue | E12: 143656271 | F12: 139606161 | G12: 143065872 | H12: 150403469 | I12: 158715818 | J12: 158447003
D15: Forecasted Revenue Using CAGR in BDT | E15: 2025 | F15: 2026 | G15: 2027 | H15: 2028 | I15: 2029 | J15: 2030
E16: =J12*(1+E1) -> 1.661276e+08 | F16: =E16*(1+E1) -> 1.741805e+08 | G16: =F16*(1+E1) -> 1.8262376e+08 | H16: =G16*(1+E1) -> 1.9147631e+08 | I16: =H16*(1+E1) -> 2.0075797e+08 | J16: =I16*(1+E1) -> 2.1048955e+08

Sheet Top-Down Based Sales forecast
A1: Top-Down Input
B2: Actual
A3: Year | B3: 2019 | C3: 2020 | D3: 2021 | E3: 2022 | F3: 2023 | G3: 2024
A4: Population | B4: =163.05*10^6 -> 163050000 | C4: =164.69*10^6 -> 164690000 | D4: =166.66*10^6 -> 166660000 | E4: =168.52*10^6 -> 168520000 | F4: =170.28*10^6 -> 170280000 | G4: =172.02*10^6 -> 172020000
A5: GDP Growth | B5: 0.1183 | C5: 0.0742 | D5: 0.1135 | E5: 0.1251 | F5: 0.1307 | G5: 0.11397
A6: Inflation | B6: 0.0548 | C6: 0.0556 | D6: 0.0565 | E6: 0.0615 | F6: 0.0902 | G6: 0.0937
A7: Total Mobile Subscriptions | B7: 165570000 | C7: 170100000 | D7: 181020000 | E7: 180200000 | F7: 190810000 | G7: 187580000
A8: Year on Year % Change | C8: =C7/B7-1 -> 0.027360029 | D8: =D7/C7-1 -> 0.064197531 | E8: =E7/D7-1 -> -0.0045298862 | F8: =F7/E7-1 -> 0.058879023 | G8: =G7/F7-1 -> -0.016927834 | I8: Expected Growth | J8: =GEOMEAN(C8+1, D8+1, E8+1, F8+1, G8+1)-1 -> 0.025276437
A9: Grameenphone Subscriptions | B9: 76460000 | C9: 79040000 | D9: 83460000 | E9: 79290000 | F9: 82200000 | G9: 84520000
A10: Year on Year % Change | C10: =C9/B9-1 -> 0.033743134 | D10: =D9/C9-1 -> 0.055921053 | E10: =E9/D9-1 -> -0.049964055 | F10: =F9/E9-1 -> 0.036700719 | G10: =G9/F9-1 -> 0.028223844 | I10: Expected Growth | J10: =GEOMEAN(C10+1, D10+1, E10+1, F10+1, G10+1)-1 -> 0.020246325
A11: Grameenphone Market Share | B11: =B9/B7 -> 0.46179864 | C11: =C9/C7 -> 0.46466784 | D11: =D9/D7 -> 0.46105403 | E11: =E9/E7 -> 0.4400111 | F11: =F9/F7 -> 0.43079503 | G11: =G9/G7 -> 0.45058109 | H11: =_xlfn.FORMULATEXT(G11) -> =G9/G7
A12: Year on Year % Change | C12: =C11/B11-1 -> 0.0062131137 | D12: =D11/C11-1 -> -0.0077772011 | E12: =E11/D11-1 -> -0.045640917 | F12: =F11/E11-1 -> -0.020945079 | G12: =G11/F11-1 -> 0.045929159 | I12: Expected Growth | J12: =GEOMEAN(C12+1, D12+1, E12+1, F12+1, G12+1)-1 -> -0.0049061037
A13: GP ARPU (BDT/month) | B13: 157 | C13: 150 | D13: 143 | E13: 149 | F13: 161 | G13: 155
A14: Year on Year % Change | C14: =C13/B13-1 -> -0.044585987 | D14: =D13/C13-1 -> -0.046666667 | E14: =E13/D13-1 -> 0.041958042 | F14: =F13/E13-1 -> 0.080536913 | G14: =G13/F13-1 -> -0.037267081 | I14: Expected Growth | J14: =GEOMEAN(D14+1, E14+1, F14+1)-1 -> 0.023870128
A15: Mobile Data Users | B15: 40600000 | C15: 41300000 | D15: 44600000 | E15: 43600000 | F15: 46600000 | G15: 48000000
A16: Smartphone Users | B16: =B15/0.95 -> 42736842 | C16: =C15/0.95 -> 43473684 | D16: =D15/0.95 -> 46947368 | E16: =E15/0.95 -> 45894737 | F16: =F15/0.95 -> 49052632 | G16: =G15/0.95 -> 50526316 | H16: =_xlfn.FORMULATEXT(G16) -> =G15/0.95
A17: Year on Year % Change | C17: =C16/B16-1 -> 0.017241379 | D17: =D16/C16-1 -> 0.079903148 | E17: =E16/D16-1 -> -0.022421525 | F17: =F16/E16-1 -> 0.068807339 | G17: =G16/F16-1 -> 0.030042918 | I17: Expected Growth | J17: =GEOMEAN(C17+1, D17+1, E17+1, F17+1, G17+1)-1 -> 0.034053576
A18: GP Revenue (BDT bn) | B18: =B9*B13*12 -> 144050640000 | C18: =C9*C13*12 -> 142272000000 | D18: =D9*D13*12 -> 143217360000 | E18: =E9*E13*12 -> 141770520000 | F18: =F9*F13*12 -> 158810400000 | G18: =G9*G13*12 -> 157207200000 | H18: =_xlfn.FORMULATEXT(G18) -> =G9*G13*12
A19: Year on Year % Change | C19: =C18/B18-1 -> -0.012347325 | D19: =D18/C18-1 -> 0.0066447368 | E19: =E18/D18-1 -> -0.010102407 | F19: =F18/E18-1 -> 0.12019339 | G19: =G18/F18-1 -> -0.010095057
C20: =_xlfn.FORMULATEXT(C19) -> =C18/B18-1 | D20: =_xlfn.FORMULATEXT(D19) -> =D18/C18-1 | E20: =_xlfn.FORMULATEXT(E19) -> =E18/D18-1 | F20: =_xlfn.FORMULATEXT(F19) -> =F18/E18-1 | G20: =_xlfn.FORMULATEXT(G19) -> =G18/F18-1
A23: Top-Down Forecast
A24: Year | B24: Industry Subscription | C24: GP Market Share (%) | D24: GP Subscription | E24: ARPU (BDT/month) | F24: GP Revenue (BDT)
A25: 2024 | B25: =B35 -> 187580000 | C25: =B36 -> 0.45058109 | D25: =B25*C25 -> 84520000 | E25: =B37 -> 155 | F25: =D25*E25*12 -> 157207200000
A26: 2025 | B26: =B25*(1+$B$40) -> 1.9232135e+08 | C26: =C25*(1+$B$41) -> 0.44837049 | D26: =B26*C26 -> 86231219 | E26: =E25*(1+$B$42) -> 158.69987 | F26: =D26*E26*12 -> 1.642186e+11
A27: 2026 | B27: =B26*(1+$B$40) -> 1.9718255e+08 | C27: =C26*(1+$B$41) -> 0.44617074 | D27: =B27*C27 -> 87977085 | E27: =E26*(1+$B$42) -> 162.48806 | F27: =D27*E27*12 -> 1.7154271e+11
A28: 2027 | B28: =B27*(1+$B$40) -> 2.0216663e+08 | C28: =C27*(1+$B$41) -> 0.44398178 | D28: =B28*C28 -> 89758297 | E28: =E27*(1+$B$42) -> 166.36667 | F28: =D28*E28*12 -> 1.7919346e+11
A29: 2028 | B29: =B28*(1+$B$40) -> 2.0727668e+08 | C29: =C28*(1+$B$41) -> 0.44180356 | D29: =B29*C29 -> 91575573 | E29: =E28*(1+$B$42) -> 170.33786 | F29: =D29*E29*12 -> 1.8718545e+11
A30: 2029 | B30: =B29*(1+$B$40) -> 2.1251589e+08 | C30: =C29*(1+$B$41) -> 0.43963602 | D30: =B30*C30 -> 93429642 | E30: =E29*(1+$B$42) -> 174.40385 | F30: =D30*E30*12 -> 1.9553387e+11
A31: 2030 | B31: =B30*(1+$B$40) -> 2.1788754e+08 | C31: =C30*(1+$B$41) -> 0.43747912 | D31: =B31*C31 -> 95321248 | E31: =E30*(1+$B$42) -> 178.56689 | F31: =D31*E31*12 -> 2.0425463e+11
A34: Base Year (Last Actual) | B34: 2024
A35: Industry Subscription | B35: =G7 -> 187580000 | D35: Forecasted Sales Growth | E35: =(F31/F26)^(1/5)-1 -> 0.044599735
A36: GP Market Share (%) | B36: =G11 -> 0.45058109
A37: ARPU (BDT/month) | B37: =G13 -> 155
A38: Forecasted Years | B38: 6
A40: Industry Growth (% p.a.) | B40: =J8 -> 0.025276437
A41: GP Share (pp/yr) | B41: =J12 -> -0.0049061037
A42: ARPU Growth (% p.a.) | B42: =J14 -> 0.023870128

Sheet Bottom-Up Based Sales forecast
B2: Historical | J2: Average YoY Growth Rate
C4: 2019 | D4: 2020 | E4: 2021 | F4: 2022 | G4: 2023 | H4: 2024 | K4: 2020 | L4: 2021 | M4: 2022 | N4: 2023 | O4: 2024
B5: Mobile Communication Revenue | C5: 141546924000 | D5: 137760475000 | E5: 140865753000 | F5: 148179973000 | G5: 156331347000 | H5: 155759617000 | J5: Voice Revenue Growth Rate | K5: =(D7/C7)-1 -> -0.071756244 | L5: =(E7/D7)-1 -> -0.08126228 | M5: =(F7/E7)-1 -> -0.04209342 | N5: =(G7/F7)-1 -> 0.013981792 | O5: =(H7/G7)-1 -> 0.040496753
B6: Mobile Communication Share - Voice | C6: 0.692 | D6: 0.66 | E6: 0.593 | F6: 0.54 | G6: 0.519 | H6: 0.542 | J6: Data Revenue Growth | K6: =(D9/C9)-1 -> 0.13930156 | L6: =(E9/D9)-1 -> 0.022541139 | M6: =(F9/E9)-1 -> 0.090252528 | N6: =(G9/F9)-1 -> 0.1992496 | O6: =(H9/G9)-1 -> -0.041319612
B7: Voice Revenue | C7: =C5*C6 -> 97950471408 | D7: =D5*D6 -> 90921913500 | E7: =E5*E6 -> 83533391529 | F7: =F5*F6 -> 80017185420 | G7: =G5*G6 -> 81135969093 | H7: =H5*H6 -> 84421712414 | J7: Bundle Revenue Growth Rate | K7: - | L7: - | M7: =(F11/E11)-1 -> 0.63765338 | N7: =(G11/F11)-1 -> -0.052801279 | O7: =(H11/G11)-1 -> -0.052259257
B8: Mobile Communication Share - Data | C8: 0.211 | D8: 0.247 | E8: 0.247 | F8: 0.256 | G8: 0.291 | H8: 0.28 | J8: Interconnection Revenue Growth Rate | K8: =(D13/C13)-1 -> -0.23666705 | L8: =(E13/D13)-1 -> -0.028585918 | M8: =(F13/E13)-1 -> -0.031123242 | N8: =(G13/F13)-1 -> 0.14543938 | O8: =(H13/G13)-1 -> -0.003657168
B9: Data Revenue | C9: =C5*C8 -> 29866400964 | D9: =D5*D8 -> 34026837325 | E9: =E5*E8 -> 34793840991 | F9: =F5*F8 -> 37934073088 | G9: =G5*G8 -> 45492421977 | H9: =H5*H8 -> 4.3612693e+10 | J9: Others (Mobile Communicarion) Revenue Growth Rate | K9: =(D15/C15)-1 -> 0.097494133 | L9: =(E15/D15)-1 -> -0.34403021 | M9: =(F15/E15)-1 -> -0.040893428 | N9: =(G15/F15)-1 -> 0.020977378 | O9: =(H15/G15)-1 -> -0.10329145
B10: Mobile Communication Share - Bundle | C10: 0 | D10: 0 | E10: 0.088 | F10: 0.137 | G10: 0.123 | H10: 0.117
B11: Bundle Revenue | C11: =C5*C10 -> 0 | D11: =D5*D10 -> 0 | E11: =E5*E10 -> 12396186264 | F11: =F5*F10 -> 20300656301 | G11: =G5*G10 -> 19228755681 | H11: =H5*H10 -> 18223875189 | J11: Lease Revenues Growth Rate | K11: =(D17/C17)-1 -> 0.020443719 | L11: =(E17/D17)-1 -> 0.10917361 | M11: =(F17/E17)-1 -> 0.032163723 | N11: =(G17/F17)-1 -> 0.1084018 | O11: =(H17/G17)-1 -> 0.12655354
B12: Mobile Communication Share - Interconnection | C12: 0.051 | D12: 0.04 | E12: 0.038 | F12: 0.035 | G12: 0.038 | H12: 0.038
B13: Interconnection Revenue | C13: =C5*C12 -> 7218893124 | D13: =D5*D12 -> 5510419000 | E13: =E5*E12 -> 5352898614 | F13: =F5*F12 -> 5.1862991e+09 | G13: =G5*G12 -> 5940591186 | H13: =H5*H12 -> 5918865446 | J13: Customer Equipment Revenue Growth Rate | K13: =(D19/C19)-1 -> -0.29362129 | L13: =(E19/D19)-1 -> 0.90168642 | M13: =(F19/E19)-1 -> 0.18314831 | N13: =(G19/F19)-1 -> 0.041760443 | O13: =(H19/G19)-1 -> 0.19169271
B14: Mobile Communication Share - Others | C14: 0.047 | D14: 0.053 | E14: 0.034 | F14: 0.031 | G14: 0.03 | H14: 0.027
B15: Others (Mobile Communication) Revenue | C15: =C5*C14 -> 6652705428 | D15: =D5*D14 -> 7301305175 | E15: =E5*E14 -> 4789435602 | F15: =F5*F14 -> 4593579163 | G15: =G5*G14 -> 4689940410 | H15: =H5*H14 -> 4205509659 | J15: Other Revenues Growth Rate | K15: =(D21/C21)-1 -> -0.62398503 | L15: =(E21/D21)-1 -> 0.4420152 | M15: =(F21/E21)-1 -> -0.36973038 | N15: =(G21/F21)-1 -> -0.34998748 | O15: =(H21/G21)-1 -> -0.093307969
B17: Lease Revenues | C17: 1538272000 | D17: 1569720000 | E17: 1741092000 | F17: 1797092000 | G17: 1991900000 | H17: 2243982000
J18: Assumptions
B19: Customer Equipment Revenue | C19: 185351000 | D19: 130928000 | E19: 248984000 | F19: 294585000 | G19: 306887000 | H19: 365715000
J20: Voice Revenue Growth Rate | K20: =AVERAGE(K5:O5) -> -0.02812668
B21: Other Revenues | C21: 385724000 | D21: 145038000 | E21: 209147000 | F21: 131819000 | G21: 85684000 | H21: 77689000 | J21: Data Revenue Growth | K21: =AVERAGE(K6:O6) -> 0.082005044
J22: Bundle Revenue Growth Rate | K22: =AVERAGE(K7:O7) -> 0.17753095
B23: Total Revenue | C23: 143656271000 | D23: 139606161000 | E23: 143065872000 | F23: 150403469000 | G23: 158715818000 | H23: 158447003000 | J23: Interconnection Revenue Growth Rate | K23: =AVERAGE(K8:O8) -> -0.030918799
J24: Others (Mobile Communicarion) Revenue Growth Rate | K24: =AVERAGE(K9:O9) -> -0.073948716
B25: Forecast
J26: Lease Revenues Growth Rate | K26: =AVERAGE(K11:O11) -> 0.079347278
C27: 2025 | D27: 2026 | E27: 2027 | F27: 2028 | G27: 2029 | H27: 2030
B28: Mobile Communication Revenue | C28: =C29+C30+C31+C32+C33 -> 1.6032592e+11 | D28: =D29+D30+D31+D32+D33 -> 1.6523228e+11 | E28: =E29+E30+E31+E32+E33 -> 1.71224e+11 | F28: =F29+F30+F31+F32+F33 -> 1.7844361e+11 | G28: =G29+G30+G31+G32+G33 -> 1.8705725e+11 | H28: =H29+H30+H31+H32+H33 -> 1.9725864e+11 | J28: Customer Equipment Revenue Growth Rate | K28: =AVERAGE(K13:O13) -> 0.20493332
B29: Voice Revenue | C29: =H7*(1+K20) -> 8.204721e+10 | D29: =C29*(1+$K$20) -> 7.9739494e+10 | E29: =D29*(1+$K$20) -> 7.7496687e+10 | F29: =E29*(1+$K$20) -> 7.5316963e+10 | G29: =F29*(1+$K$20) -> 7.3198547e+10 | H29: =G29*(1+$K$20) -> 7.1139715e+10
B30: Data Revenue | C30: =H9*(1+K21) -> 4.7189154e+10 | D30: =C30*(1+$K$21) -> 5.1058902e+10 | E30: =D30*(1+$K$21) -> 5.524599e+10 | F30: =E30*(1+$K$21) -> 5.9776439e+10 | G30: =F30*(1+$K$21) -> 6.4678409e+10 | H30: =G30*(1+$K$21) -> 6.9982365e+10 | J30: Other Revenues Growth Rate | K30: =AVERAGE(K15:O15) -> -0.19899913
B31: Bundle Revenue | C31: =H11*(1+K22) -> 2.1459177e+10 | D31: =C31*(1+$K$22) -> 2.5268845e+10 | E31: =D31*(1+$K$22) -> 2.9754847e+10 | F31: =E31*(1+$K$22) -> 3.5037253e+10 | G31: =F31*(1+$K$22) -> 4.125745e+10 | H31: =G31*(1+$K$22) -> 4.8581924e+10
B32: Interconnection Revenue | C32: =H13*(1+K23) -> 5.7358612e+09 | D32: =C32*(1+$K$23) -> 5.5585153e+09 | E32: =D32*(1+$K$23) -> 5.3866527e+09 | F32: =E32*(1+$K$23) -> 5.2201039e+09 | G32: =F32*(1+$K$23) -> 5.0587045e+09 | H32: =G32*(1+$K$23) -> 4.9022954e+09
B33: Others (Mobile Communication) Revenue | C33: =H15*(1+K24) -> 3.8945176e+09 | D33: =C33*(1+$K$24) -> 3.606523e+09 | E33: =D33*(1+$K$24) -> 3.3398253e+09 | F33: =E33*(1+$K$24) -> 3.0928495e+09 | G33: =F33*(1+$K$24) -> 2.8641372e+09 | H33: =G33*(1+$K$24) -> 2.652338e+09
B35: Lease Revenues | C35: =H17*(1+K26) -> 2.4220359e+09 | D35: =C35*(1+$K$26) -> 2.6142178e+09 | E35: =D35*(1+$K$26) -> 2.8216489e+09 | F35: =E35*(1+$K$26) -> 3.045539e+09 | G35: =F35*(1+$K$26) -> 3.2871943e+09 | H35: =G35*(1+$K$26) -> 3.5480242e+09
B37: Customer Equipment Revenue | C37: =H19*(1+K28) -> 4.4066219e+08 | D37: =C37*(1+$K$28) -> 5.3096855e+08 | E37: =D37*(1+$K$28) -> 6.397817e+08 | F37: =E37*(1+$K$28) -> 7.7089429e+08 | G37: =F37*(1+$K$28) -> 9.2887622e+08 | H37: =G37*(1+$K$28) -> 1.1192339e+09
B39: Other Revenues | C39: =H21*(1+K30) -> 62228956 | D39: =C39*(1+$K$30) -> 49845448 | E39: =D39*(1+$K$30) -> 39926247 | F39: =E39*(1+$K$30) -> 31980959 | G39: =F39*(1+$K$30) -> 25616776 | H39: =G39*(1+$K$30) -> 20519059
B41: Total Revenue | C41: =C28+C35+C37+C39 -> 1.6325085e+11 | D41: =D28+D35+D37+D39 -> 1.6842731e+11 | E41: =E28+E35+E37+E39 -> 1.7472536e+11 | F41: =F28+F35+F37+F39 -> 1.8229202e+11 | G41: =G28+G35+G37+G39 -> 1.9129893e+11 | H41: =H28+H35+H37+H39 -> 2.0194641e+11
B42: Total Revenue (adjusted in 1000s for pro forma) | C42: =C41/1000 -> 1.6325085e+08 | D42: =D41/1000 -> 1.6842731e+08 | E42: =E41/1000 -> 1.7472536e+08 | F42: =F41/1000 -> 1.8229202e+08 | G42: =G41/1000 -> 1.9129893e+08 | H42: =H41/1000 -> 2.0194641e+08
D43: =(D42-C42)/C42 -> 0.031708658 | E43: =(E42-D42)/D42 -> 0.037393264 | F43: =(F42-E42)/E42 -> 0.043306045 | G43: =(G42-F42)/F42 -> 0.049409247 | H43: =(H42-G42)/G42 -> 0.055658854
H44: =AVERAGE(D43:H43) -> 0.043495214

Sheet Assumptions
A1: Pro forma Rate Assumptions
A2: Sales growth | C2: Bottom Up Approach
A3: Current assets/Sales | C3: 0.0529
A4: Current liabilities/Sales | C4: 0.5588
A5: Net fixed assets/Sales | C5: 0.4226
A6: Costs of goods sold/Sales | C6: 0.1397
A7: Depreciation rate | C7: 0.1398
A8: Interest rate on debt | C8: 0.0989
A9: Lease Liabiltiies on Net PPE % | C9: % of total net PPE for leased assets
A10: Operating Expenses/Sales | C10: 0.1978
A11: Tax rate | C11: 0.41
A12: Dividend payout ratio | C12: 0.759
K13: Sales Forecast
K14: Years | N14: 2025 | O14: 2026 | P14: 2027 | Q14: 2028 | R14: 2029 | S14: 2030
A15: Base for the Pro Forma Assumptions [Calculations] | K15: Bottom Up Revenue | N15: 1.6325085e+08 | O15: 1.6842731e+08 | P15: 1.7472536e+08 | Q15: 1.8229202e+08 | R15: 1.9129893e+08 | S15: 2.0194641e+08
A16: Components | B16: 2019 | C16: 2020 | D16: 2021 | E16: 2022 | F16: 2023 | G16: 2024 | H16: Model Rate | K16: % change | N16: =(N15-G17)/G17 -> 0.030318297 | O16: 0.031708658 | P16: 0.037393264 | Q16: 0.043306045 | R16: 0.049409247 | S16: 0.055658854
A17: Revenue | B17: 143656271 | C17: 139606161 | D17: 143065872 | E17: 150403469 | F17: 158715818 | G17: 158447003 | K17: Bottom up implied revenue growth rate | S17: =AVERAGE(N16:S16) -> 0.041299061
A18: Average Revenue Growth rate | B18: =(B17-132831967)/132831967 -> 0.081488698 | C18: =(C17-B17)/B17 -> -0.028193061 | D18: =(D17-C17)/C17 -> 0.024781936 | E18: =(E17-D17)/D17 -> 0.051288242 | F18: =(F17-E17)/E17 -> 0.055267003 | G18: =(G17-F17)/F17 -> -0.0016936875 | H18: =AVERAGE(D18,E18,F18) -> 0.04377906 | K18: Top Down Approach | R18: Model Rate TD | S18: 0.0446
A19: Total Current Assets | B19: 7238494 | C19: 7332233 | D19: 7118916 | E19: 8767798 | F19: 8586151 | G19: 8275593
A20: Current Assets/Sales rate | B20: =B19/B17 -> 0.050387595 | C20: =C19/C17 -> 0.052520841 | D20: =D19/D17 -> 0.049759708 | E20: =E19/E17 -> 0.058295185 | F20: =F19/F17 -> 0.054097639 | G20: =G19/G17 -> 0.052229407 | H20: =AVERAGE(B20:G20) -> 0.052881729
A21: Total Current Liabilities | B21: 87491938 | C21: 75416374 | D21: 79736106 | E21: 87895358 | F21: 89078170 | G21: 79314915
A22: Current Liabilities/Sales rate | B22: =B21/B17 -> 0.60903668 | C22: =C21/C17 -> 0.54020806 | D22: =D21/D17 -> 0.55733841 | E22: =E21/E17 -> 0.58439715 | F22: =F21/F17 -> 0.56124318 | G22: =G21/G17 -> 0.50057693 | H22: =AVERAGE(B22:G22) -> 0.55880007
A23: Cost of material and traffic charges | B23: 8465283 | C23: 8812905 | D23: 9604705 | E23: 10088492 | F23: 9961041 | G23: 9825692
A24: Revenue sharing, spectrum charges and licence fees | B24: 10107313 | C24: 10478334 | D24: 10895286 | E24: 12583383 | F24: 12009842 | G24: 12068041
A25: Cost of Goods Sold | B25: 18572596 | C25: 19291239 | D25: 20499991 | E25: 22671875 | F25: 21970883 | G25: 21893733
A26: Cost of goods sold/ Sales rate | B26: =B25/B17 -> 0.12928497 | C26: =C25/C17 -> 0.13818329 | D26: =D25/D17 -> 0.14329057 | E26: =E25/E17 -> 0.15074037 | F26: =F25/F17 -> 0.13842907 | G26: =G25/G17 -> 0.13817701 | H26: =AVERAGE(B26:G26) -> 0.13968421
A27: Total Non Current Assets | B27: 62396558 | C27: 56901192 | D27: 60387950 | E27: 62849119 | F27: 67019995 | G27: 68335441
A28: Net Fixed Assets/Sales | B28: =B27/B17 -> 0.43434622 | C28: =C27/C17 -> 0.40758367 | D28: =D27/D17 -> 0.42209892 | E28: =E27/E17 -> 0.41787014 | F28: =F27/F17 -> 0.42226412 | G28: =G27/G17 -> 0.43128264 | H28: =AVERAGE(B28:G28) -> 0.42257428
A29: Interest Expense | B29: 804706 | C29: -1245125 | D29: 87206 | E29: 456720 | F29: 668820 | G29: 451408
A30: Loans and Borrowing | B30: 2934284 | C30: 1240000 | D30: 5500000 | E30: 5037394 | F30: 3119599 | G30: 5000000
A31: Interest Rate | C31: =-C29/((C30+B30)/2) -> 0.59656938 | D31: =D29/((D30+C30)/2) -> 0.025877151 | E31: =E29/((E30+D30)/2) -> 0.08668557 | F31: =F29/((F30+E30)/2) -> 0.1639869 | G31: =G29/((G30+F30)/2) -> 0.11118973 | H31: =AVERAGE(E31,G31) -> 0.098937648
A32: Income Tax Expense | B32: -29382199 | C32: -25613869 | D32: -26691690 | E32: -21898505 | F32: -21249000 | G32: -17234497
A33: Net Profit | B33: 34516760 | C33: 37187037 | D33: 34129056 | E33: 30091598 | F33: 33074873 | G33: 36308727
A34: Total Dividend Paid | B34: 26301675 | C34: 28110077 | D34: 33058662 | E34: 33584032 | F34: 9093155 | G34: 42317213
A35: Tax Rate | B35: =-B32/(B33-B32) -> 0.45982281 | C35: =-C32/(C33-C32) -> 0.40785827 | D35: =-D32/(D33-D32) -> 0.43885831 | E35: =-E32/(E33-E32) -> 0.42120526 | F35: =-F32/(F33-F32) -> 0.391154 | G35: =-G32/(G33-G32) -> 0.32188008 | H35: =AVERAGE(B35:G35) -> 0.40679646
A36: Dividend Payout Ratio | B36: =B34/B33 -> 0.76199722 | C36: =C34/C33 -> 0.75591064 | D36: =D34/D33 -> 0.96863687 | E36: =E34/E33 -> 1.1160601 | F36: =F34/F33 -> 0.27492638 | G36: =G34/G33 -> 1.1654832 | H36: =AVERAGE(B36,C36) -> 0.75895393
A37: Retention Rate | B37: =1-B36 -> 0.23800278 | C37: =1-C36 -> 0.24408936 | D37: =1-D36 -> 0.031363129 | E37: =1-E36 -> -0.1160601 | F37: =1-F36 -> 0.72507362 | G37: =1-G36 -> -0.16548325
A38: Depreciation analysis in relation with the PPE
A39: Land | B39: 1010608 | C39: 1054134 | D39: 1069921 | E39: 1228584 | F39: 1237566 | G39: 1238980
A40: Building | B40: 4046376 | C40: 4051020 | D40: 4064482 | E40: 4102681 | F40: 4116781 | G40: 3933495
A41: Base Station | B41: 134166845 | C41: 135337861 | D41: 134197356 | E41: 145555209 | F41: 156370250 | G41: 158695351
A42: Tranmission Equipment | B42: 33368535 | C42: 21537389 | D42: 21542040 | E42: 24148186 | F42: 26393634 | G42: 23399403
A43: Computer and other IT equipment | B43: 8158828 | C43: 7457619 | D43: 8322855 | E43: 9960087 | F43: 11486871 | G43: 10697295
A44: Furniture and fixtures | B44: 2933258 | C44: 2845757 | D44: 2885809 | E44: 2872750 | F44: 3015130 | G44: 1744597
A45: Vehicles | B45: 1494650 | C45: 1032658 | D45: 893196 | E45: 715233 | F45: 571824 | G45: 555943
A46: Capital-in-progress | B46: 6054735 | C46: 5710971 | D46: 7287396 | E46: 4679384 | F46: 4171177 | G46: 3493333
A47: Total | B47: =SUM(B39:B46) -> 191233835 | C47: =SUM(C39:C46) -> 179027409 | D47: =SUM(D39:D46) -> 180263055 | E47: =SUM(E39:E46) -> 193262114 | F47: =SUM(F39:F46) -> 207363233 | G47: =SUM(G39:G46) -> 203758397
A49: Depreciation Analysis (in %)
A50: Building | B50: =B40/SUM($B$40:$B$45) -> 0.021971055 | C50: =C40/SUM($C$40:$C$45) -> 0.023516579 | D50: =D40/SUM($D$40:$D$45) -> 0.023643667 | E50: =E40/SUM($E$40:$E$45) -> 0.021898 | F50: =F40/SUM($F$40:$F$45) -> 0.020384697 | G50: =G40/SUM($G$40:$G$45) -> 0.019763716
A51: Base Station | B51: =B41/SUM($B$40:$B$45) -> 0.72850054 | C51: =C41/SUM($C$40:$C$45) -> 0.78564989 | D51: =D41/SUM($D$40:$D$45) -> 0.78064501 | E51: =E41/SUM($E$40:$E$45) -> 0.77689879 | F51: =F41/SUM($F$40:$F$45) -> 0.77428459 | G51: =G41/SUM($G$40:$G$45) -> 0.79735956
A52: Tranmission Equipment | B52: =B42/SUM($B$40:$B$45) -> 0.18118482 | C52: =C42/SUM($C$40:$C$45) -> 0.12502671 | D52: =D42/SUM($D$40:$D$45) -> 0.12531309 | E52: =E42/SUM($E$40:$E$45) -> 0.12889059 | F52: =F42/SUM($F$40:$F$45) -> 0.130691 | G52: =G42/SUM($G$40:$G$45) -> 0.11756953
A53: Computer and other IT equipment | B53: =B43/SUM($B$40:$B$45) -> 0.044300889 | C53: =C43/SUM($C$40:$C$45) -> 0.043292228 | D53: =D43/SUM($D$40:$D$45) -> 0.048415225 | E53: =E43/SUM($E$40:$E$45) -> 0.053161818 | F53: =F43/SUM($F$40:$F$45) -> 0.056878513 | G53: =G43/SUM($G$40:$G$45) -> 0.053748206
A54: Furniture and fixtures | B54: =B44/SUM($B$40:$B$45) -> 0.015927035 | C54: =C44/SUM($C$40:$C$45) -> 0.016519906 | D54: =D44/SUM($D$40:$D$45) -> 0.016787159 | E54: =E44/SUM($E$40:$E$45) -> 0.015333261 | F54: =F44/SUM($F$40:$F$45) -> 0.01492975 | G54: =G44/SUM($G$40:$G$45) -> 0.0087656701
A55: Vehicles | B55: =B45/SUM($B$40:$B$45) -> 0.0081156662 | C55: =C45/SUM($C$40:$C$45) -> 0.0059946835 | D55: =D45/SUM($D$40:$D$45) -> 0.0051958475 | E55: =E45/SUM($E$40:$E$45) -> 0.0038175456 | F55: =F45/SUM($F$40:$F$45) -> 0.0028314498 | G55: =G45/SUM($G$40:$G$45) -> 0.0027933173
B56: ='Balance Sheet'!B10 -> 127,735,251 | C56: ='Balance Sheet'!C10 -> 138,253,346 | D56: ='Balance Sheet'!D10 -> 153,139,103 | E56: ='Balance Sheet'!E10 -> 172993696 | F56: ='Balance Sheet'!F10 -> 175115719 | G56: ='Balance Sheet'!G10 -> 20,526,814
A57: Net PPE/ Sales | B57: =B56/B17 -> 0.88917282 | C57: =C56/C17 -> 0.99030978 | D57: =D56/D17 -> 1.0704097 | E57: =E56/E17 -> 1.1501975 | F57: =F56/F17 -> 1.1033287 | G57: =G56/G17 -> 0.12955003
A58: Gross PPE/Sales | B58: =B47/B17 -> 1.3311903 | C58: =C47/C17 -> 1.2823747 | D58: =D47/D17 -> 1.2600004 | E58: =E47/E17 -> 1.2849578 | F58: =F47/F17 -> 1.3065064 | G58: =G47/G17 -> 1.2859719
A60: Depreciation rates | D60: Useful life
A61: Building | B61: =1/30 -> 0.033333333 | D61: 10 to 50
A62: Base Station | B62: =1/6.5 -> 0.15384615 | D62: 3 to 10
A63: Tranmission Equipment | B63: =1/18.5 -> 0.054054054 | D63: 7 to 30
A64: Computer and other IT equipment | B64: =1/7.5 -> 0.13333333 | D64: 5 to 10
A65: Furniture and fixtures | B65: =1/4 -> 0.25 | D65: 3 to 5
A66: Vehicles | B66: =1/2 -> 0.5 | D66: 4
A67: Average Depreciation Rate | B67: =SUMPRODUCT($B$61:$B$66,B50:B55) -> 0.13654953 | C67: =SUMPRODUCT($B$61:$B$66,C50:C55) -> 0.14131092 | D67: =SUMPRODUCT($B$61:$B$66,D50:D55) -> 0.14091111 | E67: =SUMPRODUCT($B$61:$B$66,E50:E55) -> 0.14005021 | F67: =SUMPRODUCT($B$61:$B$66,F50:F55) -> 0.13959654 | G67: =SUMPRODUCT($B$61:$B$66,G50:G55) -> 0.14043911
A68: Model Depreciation Rate | B68: =AVERAGE(B67:G67) -> 0.13980957
A69: Salaries and personnel cost | B69: -9437578 | C69: -10027226 | D69: -11507572 | E69: -9235728 | F69: -8494009 | G69: -8517867
A70: Operation and maintenance | B70: -5898863 | C70: -4984745 | D70: -5550948 | E70: -4252580 | F70: -6272385 | G70: -6942686
A71: Sales, marketing and commissions | B71: -13480018 | C71: -11771112 | D71: -13341089 | E71: -15278933 | F71: -15428172 | G71: -16247666
A72: Operating Expenses | B72: =-SUM(B69:B71) -> 28816459 | C72: =-SUM(C69:C71) -> 26783083 | D72: =-SUM(D69:D71) -> 30399609 | E72: =-SUM(E69:E71) -> 28767241 | F72: =-SUM(F69:F71) -> 30194566 | G72: =-SUM(G69:G71) -> 31708219
A73: Operating Expenses/ Sales | B73: =B72/B17 -> 0.20059312 | C73: =C72/C17 -> 0.19184743 | D73: =D72/D17 -> 0.2124868 | E73: =E72/E17 -> 0.19126714 | F73: =F72/F17 -> 0.19024295 | G73: =G72/G17 -> 0.20011877 | H73: =AVERAGE(B73:G73) -> 0.19775937
A74: Rights-of-use asset components | B74: Value of Net PPE | C74: % of total ppe | D74: % of total net ppe for leased
A75: Land | B75: 1238980 | C75: =B75/68335330 -> 0.018130885 | D75: =C75/$C$79 -> 0.020371491
A76: Building | B76: 1361592 | C76: =B76/68335330 -> 0.019925154 | D76: =C76/$C$79 -> 0.022387495
A77: Base Station | B77: 52278930 | C77: =B77/68335330 -> 0.76503516 | D77: =C77/$C$79 -> 0.85957784
A78: Tranmission Equipment | B78: 5939807 | C78: =B78/68335330 -> 0.086921465 | D78: =C78/$C$79 -> 0.097663178
C79: =SUM(C75:C79) -> 0.89001266 | D79: =C79/$C$79 -> 1

Sheet Pro Forma Balance Sheets
A1: Income Statement
A2: Particulars | B2: 2024 (in 000 BDT) | C2: 2025 (in 000 BDT) | D2: 2026 (in 000 BDT) | E2: 2027 (in 000 BDT) | F2: 2028 (in 000 BDT) | G2: 2029 (in 000 BDT) | H2: 2030 (in 000 BDT)
A3: Revenue | B3: 158447003 | C3: ='Bottom-Up Based Sales forecast'!C42 -> 1.6325085e+08 | D3: ='Bottom-Up Based Sales forecast'!D42 -> 1.6842731e+08 | E3: ='Bottom-Up Based Sales forecast'!E42 -> 1.7472536e+08 | F3: ='Bottom-Up Based Sales forecast'!F42 -> 1.8229202e+08 | G3: ='Bottom-Up Based Sales forecast'!G42 -> 1.9129893e+08 | H3: ='Bottom-Up Based Sales forecast'!H42 -> 2.0194641e+08
A4: Cost of material and traffic charges | B4: -9825692
A5: Revenue sharing, spectrum charges and licence fees | B5: -12068041
A6: Cost of Goods Sold | B6: =SUM(B4:B5) -> -21893733 | C6: =-C3*$Q$16 -> -22806143 | D6: =-D3*$Q$16 -> -23529295 | E6: =-E3*$Q$16 -> -24409133 | F6: =-F3*$Q$16 -> -25466196 | G6: =-G3*$Q$16 -> -26724461 | H6: =-H3*$Q$16 -> -28211914
A7: Gross Profit | B7: =B3+B4+B5 -> 136553270 | C7: =SUM(C3:C6) -> 1.404447e+08 | D7: =SUM(D3:D6) -> 1.4489802e+08 | E7: =SUM(E3:E6) -> 1.5031623e+08 | F7: =SUM(F3:F6) -> 1.5682583e+08 | G7: =SUM(G3:G6) -> 1.6457447e+08 | H7: =SUM(H3:H6) -> 1.737345e+08
A8: Salaries and personnel cost | B8: -8517867
A9: Operation and maintenance | B9: -6942686
A10: Sales, marketing and commissions | B10: -16247666
A11: Operating Expenses | B11: -31708219 | C11: =-C3*$Q$20 -> -32291017 | D11: =-D3*$Q$20 -> -33314922 | E11: =-E3*$Q$20 -> -34560676 | F11: =-F3*$Q$20 -> -36057362 | G11: =-G3*$Q$20 -> -37838929 | H11: =-H3*$Q$20 -> -39945001 | O11: Pro forma Rate Assumptions
A12: Depreciation expenses | B12: -14497727 | C12: =-$Q$17*(C44+B44)/2 -> -29479847 | D12: =-$Q$17*(D44+C44)/2 -> -32701364 | E12: =-$Q$17*(E44+D45)/2 -> -37571727 | F12: =-$Q$17*(F44+E45)/2 -> -41797946 | G12: =-$Q$17*(G44+F45)/2 -> -46457933 | H12: =-$Q$17*(H44+G45)/2 -> -51594172 | O12: Sales growth | Q12: Bottom-up Approach forecast
A13: Amortization expenses | B13: =-34551840+14497727 -> -20054113 | C13: =B13 -> -20054113 | D13: =C13 -> -20054113 | E13: =D13 -> -20054113 | F13: =E13 -> -20054113 | G13: =F13 -> -20054113 | H13: =G13 -> -20054113 | O13: Current assets/Sales | Q13: 0.0529
A14: Other operating (expenses)/income | B14: =-11164000 -> -11164000 | C14: =-11164000 -> -11164000 | D14: =-11164000 -> -11164000 | E14: =-11164000 -> -11164000 | F14: =-11164000 -> -11164000 | G14: =-11164000 -> -11164000 | H14: =-11164000 -> -11164000 | O14: Current liabilities/Sales | Q14: 0.5588
A15: Total Operating Expenses | B15: =SUM(B11:B14) -> -77424059 | C15: =SUM(C11:C14) -> -92988977 | D15: =SUM(D11:D14) -> -97234399 | E15: =SUM(E11:E14) -> -1.0335052e+08 | F15: =SUM(F11:F14) -> -1.0907342e+08 | G15: =SUM(G11:G14) -> -1.1551498e+08 | H15: =SUM(H11:H14) -> -1.2275729e+08 | O15: Net fixed assets/Sales | Q15: 0.4226
A16: Operating Profit | B16: =B7+B15 -> 59129211 | C16: =C7+C15 -> 47455726 | D16: =D7+D15 -> 47663617 | E16: =E7+E15 -> 46965710 | F16: =F7+F15 -> 47752406 | G16: =G7+G15 -> 49059498 | H16: =H7+H15 -> 50977214 | O16: Costs of goods sold/Sales | Q16: 0.1397
A17: Interest Expense | B17: 451408 | C17: =$Q$18*(B86+C86)/2 -> 494500 | D17: =$Q$18*(C86+D86)/2 -> 494500 | E17: =$Q$18*(D86+E86)/2 -> 494500 | F17: =$Q$18*(E86+F86)/2 -> 494500 | G17: =$Q$18*(F86+G86)/2 -> 494500 | H17: =$Q$18*(G86+H86)/2 -> 494500 | O17: Depreciation rate | Q17: 0.1398
A18: Interest Income | B18: 715732 | C18: 715732 | D18: 715732 | E18: 715732 | F18: 715732 | G18: 715732 | H18: 715732 | O18: Interest rate on debt | Q18: 0.0989
A19: Interest expenses on lease liabilities | B19: 4949247 | C19: =B19 -> 4949247 | D19: =C19 -> 4949247 | E19: =D19 -> 4949247 | F19: =E19 -> 4949247 | G19: =F19 -> 4949247 | H19: =G19 -> 4949247 | O19: Lease Liabiltiies on Net PPE % | Q19: % of total net PPE for leased assets | U19: Leased PPE | V19: % of total net ppe for leased
A20: Net interest cost on defined benefit obligation | B20: 101305 | C20: =B20 -> 101305 | D20: =C20 -> 101305 | E20: =D20 -> 101305 | F20: =E20 -> 101305 | G20: =F20 -> 101305 | H20: =G20 -> 101305 | O20: Operating Expenses/Sales | Q20: 0.1978 | U20: Land | V20: 0.020371491
A21: Other Finance Expenses | B21: 200405 | C21: =B21 -> 200405 | D21: =C21 -> 200405 | E21: =D21 -> 200405 | F21: =E21 -> 200405 | G21: =F21 -> 200405 | H21: =G21 -> 200405 | O21: Tax rate | Q21: 0.41 | U21: Building | V21: 0.022387495
A22: Finance (expense) | B22: =B19+(B20+B21+B17-B18) -> 4986633 | C22: =C19+(C20+C21+C17-C18) -> 5029725 | D22: =D19+(D20+D21+D17-D18) -> 5029725 | E22: =E19+(E20+E21+E17-E18) -> 5029725 | F22: =F19+(F20+F21+F17-F18) -> 5029725 | G22: =G19+(G20+G21+G17-G18) -> 5029725 | H22: =H19+(H20+H21+H17-H18) -> 5029725 | O22: Dividend payout ratio | Q22: 0.759 | U22: Base Station | V22: 0.85957784
A23: Foreign exchange (loss)/gain | B23: -599394 | C23: -599394 | D23: -599394 | E23: -599394 | F23: -599394 | G23: -599394 | H23: -599394 | U23: Tranmission Equipment | V23: 0.097663178
A24: Profit before tax | B24: =B16-B22+B23 -> 53543184 | C24: =C16-C22+C23 -> 41826607 | D24: =D16-D22+D23 -> 42034498 | E24: =E16-E22+E23 -> 41336591 | F24: =F16-F22+F23 -> 42123287 | G24: =G16-G22+G23 -> 43430379 | H24: =H16-H22+H23 -> 45348095 | U24: Total | V24: =SUM(V20:V23) -> 1
A25: Income tax expense | B25: -17234497 | C25: =-C24*$Q$21 -> -17148909 | D25: =-D24*$Q$21 -> -17234144 | E25: =-E24*$Q$21 -> -16948002 | F25: =-F24*$Q$21 -> -17270548 | G25: =-G24*$Q$21 -> -17806455 | H25: =-H24*$Q$21 -> -18592719
A26: Profit after tax | B26: =B24+B25 -> 36308687 | C26: =C24+C25 -> 24677698 | D26: =D24+D25 -> 24800354 | E26: =E24+E25 -> 24388589 | F26: =F24+F25 -> 24852739 | G26: =G24+G25 -> 25623924 | H26: =H24+H25 -> 26755376
A27: Other comprehensive income
A28: Item that will not be reclassified subsequently to profit or loss
A29: Remeasurement of defined benefit plan | B29: 379566 | C29: =B29 -> 379566 | D29: =C29 -> 379566 | E29: =D29 -> 379566 | F29: =E29 -> 379566 | G29: =F29 -> 379566 | H29: =G29 -> 379566
A30: Related taxes | B30: -151826 | C30: =B30 -> -151826 | D30: =C30 -> -151826 | E30: =D30 -> -151826 | F30: =E30 -> -151826 | G30: =F30 -> -151826 | H30: =G30 -> -151826
A31: Total comprehensive income for the year | B31: =B26-B29+B30 -> 35777295 | C31: =C26-C29+C30 -> 24146306 | D31: =D26-D29+D30 -> 24268962 | E31: =E26-E29+E30 -> 23857197 | F31: =F26-F29+F30 -> 24321347 | G31: =G26-G29+G30 -> 25092532 | H31: =H26-H29+H30 -> 26223984
A32: Earnings per share
A33: Basic earnings per share
A34: (per value BDT 10 each in BDT) | B34: =B26/1350300 -> 26.889348 | C34: =C26/1350300 -> 18.275715 | D34: =D26/1350300 -> 18.366551 | E34: =E26/1350300 -> 18.061607 | F34: =F26/1350300 -> 18.405347 | G34: =G26/1350300 -> 18.976467 | H34: =H26/1350300 -> 19.814394
A35: Dividend Payout | B35: =B26*122.73% -> 44561652 | C35: =C26*$Q$22 -> 18730373 | D35: =D26*$Q$22 -> 18823468 | E35: =E26*$Q$22 -> 18510939 | F35: =F26*$Q$22 -> 18863229 | G35: =G26*$Q$22 -> 19448558 | H35: =H26*$Q$22 -> 20307330
A36: Retained Earnings | B36: =B26-B35 -> -8252964.6 | C36: =C26-C35 -> 5947325.2 | D36: =D26-D35 -> 5976885.3 | E36: =E26-E35 -> 5877649.8 | F36: =F26-F35 -> 5989510.2 | G36: =G26-G35 -> 6175365.6 | H36: =H26-H35 -> 6448045.7
A37: Retained Earnings (value only) | C37: 5947325.2 | D37: 5976885.3 | E37: 5877649.8 | F37: 5989510.2 | G37: 6175365.6 | H37: 6448045.7
A40: Balance Sheet
A41: Particulars | B41: 2024 | C41: 2025 | D41: 2026 | E41: 2027 | F41: 2028 | G41: 2029 | H41: 2030
A42: Assets
A43: Non-current assets
A44: Property, plant and equipment- Gross | B44: 203758397 | C44: 2.1798476e+08 | D44: 2.4984591e+08 | E44: 2.6872517e+08 | F44: 2.8895281e+08 | G44: 3.1062368e+08 | H44: 3.3383924e+08
C45: =C47+C46 -> 2.3389272e+08 | D45: =SUM(D46:D47) -> 2.6878166e+08 | E45: =SUM(E46:E47) -> 3.0901494e+08 | F45: =SUM(F46:F47) -> 3.5401056e+08 | G45: =SUM(G46:G47) -> 4.0427481e+08 | H45: =SUM(H46:H47) -> 4.6036861e+08
A46: Accumulated Depreciation | B46: 135423067 | C46: =B46-C12 -> 1.6490291e+08 | D46: =C46-D12 -> 1.9760428e+08 | E46: =D46-E12 -> 2.3517601e+08 | F46: =E46-F12 -> 2.7697395e+08 | G46: =F46-G12 -> 3.2343188e+08 | H46: =G46-H12 -> 3.7502606e+08
A47: Property, plant and equipment- Net | B47: =B44-B46 -> 68335330 | C47: =C3*$Q$15 -> 68989808 | D47: =D3*$Q$15 -> 71177382 | E47: =E3*$Q$15 -> 73838937 | F47: =F3*$Q$15 -> 77036609 | G47: =G3*$Q$15 -> 80842930 | H47: =H3*$Q$15 -> 85342555
A48: Intangible assets | B48: 4774439 | C48: =B48 -> 4774439 | D48: =C48 -> 4774439 | E48: =D48 -> 4774439 | F48: =E48 -> 4774439 | G48: =F48 -> 4774439 | H48: =G48 -> 4774439
A49: Right-of-use assets- net | B49: 77710892 | C49: =B49 -> 77710892 | D49: =C49 -> 77710892 | E49: =D49 -> 77710892 | F49: =E49 -> 77710892 | G49: =F49 -> 77710892 | H49: =G49 -> 77710892
A50: Contract cost | B50: 10436997 | C50: =B50 -> 10436997 | D50: =C50 -> 10436997 | E50: =D50 -> 10436997 | F50: =E50 -> 10436997 | G50: =F50 -> 10436997 | H50: =G50 -> 10436997
A51: Deferred Tax Assets | B51: 1458619 | C51: =B51 -> 1458619 | D51: =C51 -> 1458619 | E51: =D51 -> 1458619 | F51: =E51 -> 1458619 | G51: =F51 -> 1458619 | H51: =G51 -> 1458619
A52: Other non-current assets | B52: 20526814 | C52: 20526814 | D52: 20526814 | E52: 20526814 | F52: 20526814 | G52: 20526814 | H52: 20526814
A53: Total non-current assets | B53: =SUM(B47:B52) -> 183243091 | C53: =SUM(C47:C52) -> 1.8389757e+08 | D53: =SUM(D47:D52) -> 1.8608514e+08 | E53: =SUM(E47:E52) -> 1.887467e+08 | F53: =SUM(F47:F52) -> 1.9194437e+08 | G53: =SUM(G47:G52) -> 1.9575069e+08 | H53: =SUM(H47:H52) -> 2.0025032e+08
A54: Current assets
A55: Inventories | B55: 407655
A56: Trade receivables and others | B56: 7867938
A57: Cash and cash equivalents | B57: 7334432 | C57: =C87-C58-C53 -> 44312593 | D57: =D87-D58-D53 -> 52908252 | E57: =E87-E58-E53 -> 61972084 | F57: =F87-F58-F53 -> 71789570 | G57: =G87-G58-G53 -> 82521532 | H57: =H87-H58-H53 -> 94356138
A58: Total current assets | B58: =B55+B56 -> 8275593 | C58: =C3*$Q$13 -> 8635969.8 | D58: =D3*$Q$13 -> 8909804.8 | E58: =E3*$Q$13 -> 9242971.5 | F58: =F3*$Q$13 -> 9643248 | G58: =G3*$Q$13 -> 10119714 | H58: =H3*$Q$13 -> 10682965
A59: Total assets | B59: =B58+B53+B57 -> 198853116 | C59: =C58+C53+C57 -> 2.3684613e+08 | D59: =D58+D53+D57 -> 2.479032e+08 | E59: =E58+E53+E57 -> 2.5996175e+08 | F59: =F58+F53+F57 -> 2.7337719e+08 | G59: =G58+G53+G57 -> 2.8839194e+08 | H59: =H58+H53+H57 -> 3.0528942e+08
A60: Equity and liabilities
A61: Shareholders’ equity
A62: Share capital | B62: 13503000 | C62: =B62 -> 13503000 | D62: =C62 -> 13503000 | E62: =D62 -> 13503000 | F62: =E62 -> 13503000 | G62: =F62 -> 13503000 | H62: =G62 -> 13503000
A63: Share premium | B63: 7840226 | C63: =B63 -> 7840226 | D63: =C63 -> 7840226 | E63: =D63 -> 7840226 | F63: =E63 -> 7840226 | G63: =F63 -> 7840226 | H63: =G63 -> 7840226
A64: Capital reserve | B64: 14446 | C64: =B64 -> 14446 | D64: =C64 -> 14446 | E64: =D64 -> 14446 | F64: =E64 -> 14446 | G64: =F64 -> 14446 | H64: =G64 -> 14446
A65: Retained earnings | B65: 43384785 | C65: =B65+C37 -> 49332110 | D65: =C65+D37 -> 55308995 | E65: =D65+E37 -> 61186645 | F65: =E65+F37 -> 67176156 | G65: =F65+G37 -> 73351521 | H65: =G65+H37 -> 79799567
A66: Total equity | B66: =SUM(B62:B65) -> 64742457 | C66: =SUM(C62:C65) -> 70689782 | D66: =SUM(D62:D65) -> 76666667 | E66: =SUM(E62:E65) -> 82544317 | F66: =SUM(F62:F65) -> 88533828 | G66: =SUM(G62:G65) -> 94709193 | H66: =SUM(H62:H65) -> 1.0115724e+08
A67: Non-current liabilities
A68: Rights-of-use asset components
A69: Land | C69: =C47*$V$20 -> 1405425.2 | D69: =D47*$V$20 -> 1449989.4 | E69: =E47*$V$20 -> 1504209.2 | F69: =F47*$V$20 -> 1569350.6 | G69: =G47*$V$20 -> 1646891 | H69: =H47*$V$20 -> 1738555.1
A70: Building | C70: =C47*$V$21 -> 1544509 | D70: =D47*$V$21 -> 1593483.3 | E70: =E47*$V$21 -> 1653068.9 | F70: =F47*$V$21 -> 1724656.7 | G70: =G47*$V$21 -> 1809870.7 | H70: =H47*$V$21 -> 1910606
A71: Base Station | C71: =C47*$V$22 -> 59302110 | D71: =D47*$V$22 -> 61182500 | E71: =E47*$V$22 -> 63470313 | F71: =F47*$V$22 -> 66218962 | G71: =G47*$V$22 -> 69490791 | H71: =H47*$V$22 -> 73358568
A72: Tranmission Equipment | C72: =C47*$V$23 -> 6737763.9 | D72: =D47*$V$23 -> 6951409.3 | E72: =E47*$V$23 -> 7211345.2 | F72: =F47*$V$23 -> 7523640 | G72: =G47*$V$23 -> 7895377.4 | H72: =H47*$V$23 -> 8334825.1
A73: Lease liabilities | B73: 48853886 | C73: =SUM(C69:C72) -> 68989808 | D73: =SUM(D69:D72) -> 71177382 | E73: =SUM(E69:E72) -> 73838937 | F73: =SUM(F69:F72) -> 77036609 | G73: =SUM(G69:G72) -> 80842930 | H73: =SUM(H69:H72) -> 85342555
A74: Deferred tax liabilities | B74: - | C74: =B74 -> - | D74: =C74 -> - | E74: =D74 -> - | F74: =E74 -> - | G74: =F74 -> - | H74: =G74 -> -
A75: Employee benefits | B75: 395836 | C75: =B75 -> 395836 | D75: =C75 -> 395836 | E75: =D75 -> 395836 | F75: =E75 -> 395836 | G75: =F75 -> 395836 | H75: =G75 -> 395836
A76: Other non-current liabilities | B76: 546133 | C76: =B76 -> 546133 | D76: =C76 -> 546133 | E76: =D76 -> 546133 | F76: =E76 -> 546133 | G76: =F76 -> 546133 | H76: =G76 -> 546133
A77: Total non-current liabilities | B77: =SUM(B73,B74,B75,B76) -> 49795855 | C77: =SUM(C73,C75,C74,C76) -> 69931777 | D77: =SUM(D73,D75,D74,D76) -> 72119351 | E77: =SUM(E73,E75,E74,E76) -> 74780906 | F77: =SUM(F73,F75,F74,F76) -> 77978578 | G77: =SUM(G73,G75,G74,G76) -> 81784899 | H77: =SUM(H73,H75,H74,H76) -> 86284524
A78: Current liabilities
A79: Trade payables and others | B79: 28366808
A80: Provisions | B80: 24920485
A81: Lease liabilities | B81: 11112469
A82: Current tax liabilities | B82: 12769919
A83: Other current liabilities | B83: 2077180
A84: Unclaimed Dividend | B84: 68054
A85: Total current liabilities | B85: =SUM(B79:B84) -> 79314915 | C85: =C3*$Q$14 -> 91224573 | D85: =D3*$Q$14 -> 94117182 | E85: =E3*$Q$14 -> 97636530 | F85: =F3*$Q$14 -> 1.0186478e+08 | G85: =G3*$Q$14 -> 1.0689784e+08 | H85: =H3*$Q$14 -> 1.1284766e+08
A86: Loans and borrowings | B86: 5000000 | C86: =MAX(C58+C47-C66-C77-C85,B86) -> 5000000 | D86: =MAX(D58+D47-D66-D77-D85,C86) -> 5000000 | E86: =MAX(E58+E47-E66-E77-E85,D86) -> 5000000 | F86: =MAX(F58+F47-F66-F77-F85,E86) -> 5000000 | G86: =MAX(G58+G47-G66-G77-G85,F86) -> 5000000 | H86: =MAX(H58+H47-H66-H77-H85,G86) -> 5000000
A87: Total equity and liabilities | B87: =B66+B77+B85+B86 -> 198853227 | C87: =C66+C77+C85+C86 -> 2.3684613e+08 | D87: =D66+D77+D85+D86 -> 2.479032e+08 | E87: =E66+E77+E85+E86 -> 2.5996175e+08 | F87: =F66+F77+F85+F86 -> 2.7337719e+08 | G87: =G66+G77+G85+G86 -> 2.8839194e+08 | H87: =H66+H77+H85+H86 -> 3.0528942e+08

Sheet FCFF

Sheet DDM
A1: No of Outstanding Shares (16 May 2025) | B1: 1350300022 | C1: taken from DSE
A2: Average Dividend Payout Ratio | B2: 0.759
A4: Year | D4: 2025 | E4: 2026 | F4: 2027 | G4: 2028 | H4: 2029 | I4: 2030 | L4: gotta find graph for YoY dividend payout rario
A5: From Pro Forma Income Statement:
A6: Profit After Tax | D6: 2.4677698e+10 | E6: 2.4800354e+10 | F6: 2.4388589e+10 | G6: 2.4852739e+10 | H6: 2.5623924e+10 | I6: 2.6755376e+10
A7: Dividends | D7: 1.8730373e+10 | E7: 1.8823468e+10 | F7: 1.8510939e+10 | G7: 1.8863229e+10 | H7: 1.9448558e+10 | I7: 2.030733e+10
A8: Earning Per Share (EPS) | D8: =D6/$B$1 -> 18.275715 | E8: =E6/$B$1 -> 18.366551 | F8: =F6/$B$1 -> 18.061607 | G8: =G6/$B$1 -> 18.405346 | H8: =H6/$B$1 -> 18.976467 | I8: =I6/$B$1 -> 19.814394
A9: Dividend per Share | D9: =D7/$B$1 -> 13.871267 | E9: =E7/$B$1 -> 13.940212 | F9: =F7/$B$1 -> 13.70876 | G9: =G7/$B$1 -> 13.969658 | H9: =H7/$B$1 -> 14.403138 | I9: =I7/$B$1 -> 15.039125
A11: Terminal Value using Gordon Model | C11: =I9*(1+B27)/(B24-B27) -> 199.25611
A12: Terminal Value using Industry P/E | C12: =I8*B38 -> 278.59037
A14: Total CF Gordon | C14: =D9 -> 13.871267 | D14: =E9 -> 13.940212 | E14: =F9 -> 13.70876 | F14: =G9 -> 13.969658 | G14: =H9 -> 14.403138 | H14: =I9+C11 -> 214.29524
A15: Present Value Gordon | C15: =C14/(1+$B$24)^C16 -> 12.199952 | D15: =D14/(1+$B$24)^D16 -> 10.783341 | E15: =E14/(1+$B$24)^E16 -> 9.3266163 | F15: =F14/(1+$B$24)^F16 -> 8.3589877 | G15: =G14/(1+$B$24)^G16 -> 7.5799621 | H15: =H14/(1+$B$24)^H16 -> 99.189203
A16: Year | C16: 1 | D16: 2 | E16: 3 | F16: 4 | G16: 5 | H16: 6
A17: Intrinsic Value/Share | C17: =SUM(C15:H15) -> 147.43806 | D17: Using Gordon
A19: Total CF P/E | C19: =D9 -> 13.871267 | D19: =E9 -> 13.940212 | E19: =F9 -> 13.70876 | F19: =G9 -> 13.969658 | G19: =H9 -> 14.403138 | H19: =I9+C12 -> 293.6295
A20: Present Value P/E | C20: =C19/(1+$B$24)^C16 -> 12.199952 | D20: =D19/(1+$B$24)^D16 -> 10.783341 | E20: =E19/(1+$B$24)^E16 -> 9.3266163 | F20: =F19/(1+$B$24)^F16 -> 8.3589877 | G20: =G19/(1+$B$24)^G16 -> 7.5799621 | H20: =H19/(1+$B$24)^H16 -> 135.91005
A21: Intrinsic Value/Share | C21: =SUM(C20:H20) -> 184.15891 | D21: Using Industry P/E
A23: Current Price (Jan 02, 2026) | B23: 256.5 | C23: Overvalued Or Under valued Decision
A24: Required Return | B24: =B26+B25*(B28-B26) -> 0.1369936
A25: Beta | B25: 0.851 | C25: taken from Beta calculation
A26: Risk Free Rate | B26: 0.1084 | C26: Bangladesh Bank T-Bond 364 days
A27: Long-Term Growth Rate | B27: 0.0572 | C27: https://tradingeconomics.com/bangladesh/gdp-growth#:~:text=GDP%20Growth%20Rate%20in%20Bangladesh,statistics%2C%20economic%20calendar%20and%20news.
A28: Market Return | B28: 0.142 | C28: taken from Market Return calculation
A29: P/E of GP (January, 02, 2026) | B29: =G75 -> 12.600957
A31: Peer Companies (January, 02, 2026) | B31: P/E
A32: GP | B32: 9.54
A34: ROBI | B34: 21.19
A36: BSCPLC | B36: 11.45
A38: Industry P/E | B38: =AVERAGE(B32:B37) -> 14.06
A42: Sensitivity Gordon
A43: Growth Rate | B43: Required Return
A44: =C17 -> 147.43806 | B44: =C44-0.005 -> 0.127 | C44: =D44-0.005 -> 0.132 | D44: 0.137 | E44: =D44+0.005 -> 0.142 | F44: =E44+0.005 -> 0.147 | G44: =F44+0.005 -> 0.152
A45: 0.045 | B45: 150.31829 | C45: 141.83662 | D45: 134.27464 | E45: 127.49017 | F45: 121.36892 | G45: 115.81794
A46: 0.05 | B46: 156.8687 | C46: 147.5072 | D46: 139.21869 | E46: 131.8283 | F46: 125.1972 | G46: 119.21378
A47: 0.055 | B47: 164.32889 | C47: 153.91421 | D47: 144.76568 | E47: 136.66507 | F47: 129.4416 | G47: 122.95969
A48: 0.0572 | B48: 167.94996 | C48: 157.00466 | D48: 147.42657 | E48: 138.97394 | F48: 131.45887 | G48: 124.73308
A49: 0.06 | B49: 172.90253 | C49: 161.21109 | D49: 151.03306 | E49: 142.09168 | F49: 134.17385 | G49: 127.11278
A50: 0.065 | B50: 182.85903 | C50: 169.59706 | D50: 158.1709 | E50: 148.22305 | F50: 139.48322 | G50: 131.74323
A51: 0.07 | B51: 194.56228 | C51: 179.3356 | D51: 166.37409 | E51: 155.206 | F51: 145.48211 | G51: 136.93836
A53: Value Ranges From | B53: =MIN(B45:G51) -> 115.81794
A54: Value Ranges To | B54: =MAX(B45:G51) -> 194.56228
A56: Sensitivity P/E
A57: P/E Ratio | B57: Required Return
A58: =C21 -> 184.15891 | B58: 0.117 | C58: 0.127 | D58: 0.137 | E58: 0.14 | F58: 0.145 | G58: 0.147
A59: 12.06 | B59: 181.45675 | C59: 173.40481 | D59: 165.81151 | E59: 163.61835 | F59: 160.04656 | G59: 158.64642
A60: 13.06 | B60: 191.65819 | C60: 183.07505 | D60: 174.98254 | E60: 172.64552 | F60: 168.83978 | G60: 167.34804
A61: 14.06 | B61: 201.85964 | C61: 192.74529 | D61: 184.15357 | E61: 181.67269 | F61: 177.633 | G61: 176.04967
A62: 15.5 | B62: 216.54972 | C62: 206.67044 | D62: 197.35985 | E62: 194.67182 | F62: 190.29524 | G62: 188.58
A63: 16 | B63: 221.65044 | C63: 211.50556 | D63: 201.94536 | E63: 199.1854 | F63: 194.69185 | G63: 192.93082
A64: 16.5 | B64: 226.75117 | C64: 216.34068 | D64: 206.53087 | E64: 203.69899 | F64: 199.08845 | G64: 197.28163
A65: 17 | B65: 231.85189 | C65: 221.1758 | D65: 211.11639 | E65: 208.21257 | F65: 203.48506 | G65: 201.63244
A67: Value Ranges From | B67: =MIN(B59:G65) -> 158.64642
A68: Value Ranges To | B68: =MAX(B59:G65) -> 231.85189
A71: GP (P/E Ratio) | B71: Years
B72: 2020 | C72: 2021 | D72: 2022 | E72: 2023 | F72: 2024
A73: Share Price (at year end) | B73: 347.1 | C73: 349.5 | D73: 286.6 | E73: 286.6 | F73: 323.1 | G73: taken from financial report
A74: Earnings per share | B74: 27.54 | C74: 25.28 | D74: 22.29 | E74: 24.49 | F74: 26.89
A75: P/E Ratio | B75: =B73/B74 -> 12.603486 | C75: =C73/C74 -> 13.825158 | D75: =D73/D74 -> 12.857784 | E75: =E73/E74 -> 11.702736 | F75: =F73/F74 -> 12.015619 | G75: =AVERAGE(B75:F75) -> 12.600957

Sheet Relative Valuation
A1: SL No. | B1: Company Name | C1: Market Price | D1: EPS | E1: BVPS | F1: EV | G1: Revenue/Share | H1: P/E | I1: P/B | J1: P/S | K1: EV/EBITDA | L1: ROA | M1: ROE
A2: 1 | B2: Grameenphone Ltd. | C2: 256.5 | D2: 26.89 | E2: =C9/C10 -> 47.94672 | F2: =C13+C14-C15 -> 1.2711823e+08 | G2: =C11/C10 -> 88.482821 | H2: =C2/D2 -> 9.538862 | I2: =C2/E2 -> 5.3496882 | J2: =C2/G2 -> 2.8988678 | K2: =F2/C12 -> 1.3569265 | L2: 14.5 | M2: 54.8
A3: 2 | B3: Robi Axiata PLC. | C3: 28.4 | D3: 1.34 | E3: =D9/D10 -> 13.078636 | F3: =D13+D14-D15 -> 1.3620033e+08 | G3: =D11/D10 -> 18.996494 | H3: =C3/D3 -> 21.19403 | I3: =C3/E3 -> 2.1714802 | J3: =C3/G3 -> 1.4950127 | K3: =F3/D12 -> 2.6802647 | L3: 4.5 | M3: 14
A4: 3 | B4: Bangladesh Submarine Cables PLC | C4: 127.1 | D4: 11.097 | E4: =E9/E10 -> 90.988369 | F4: =E13+E14-E15 -> -6.1279965e+09 | G4: =E11/E10 -> 21.308324 | H4: =C4/D4 -> 11.453546 | I4: =C4/E4 -> 1.3968818 | J4: =C4/G4 -> 5.9648052 | K4: =F4/E12 -> -2.5438316 | L4: 9.5 | M4: 13.5
G5: Industry Average | H5: =AVERAGE(H2:H4) -> 14.062146 | I5: =AVERAGE(I2:I4) -> 2.9726834 | J5: =AVERAGE(J2:J4) -> 3.4528952 | K5: =AVERAGE(K2:K4) -> 0.49778653 | L5: =AVERAGE(L2:L4) -> 9.5 | M5: =AVERAGE(M2:M4) -> 27.433333
B7: Industry | C7: Telecommunication | G7: Relative Valuation
B8: Trading Code | C8: GP | D8: ROBI | E8: BSCPLC | G8: Grameenphone Ltd.
B9: Shareholders Equity | C9: 64742457000 | D9: 68505020000 | E9: 17018359255 | G9: Multiples | H9: =H5*D2 -> 378.1311
B10: Number of Shares | C10: 1350300022 | D10: 5237932895 | E10: 187038843 | H10: =I5*E2 -> 142.53042
B11: Revenue | C11: 119478355000 | D11: 99502359000 | E11: 3985484227 | H11: =J5*G2 -> 305.52191
B12: EBITDA | C12: 93681000 | D12: 50816000 | E12: =C19+D19 -> 2408963110 | H12: =K5*F2 -> 63277745
B13: Market Cap of Equity | C13: 341895.97 | D13: 151900.05 | E13: 23791.341 | G13: Enterprise Value | H13: =AVERAGE(H9:H12) -> 15819643
B14: Total Debt | C14: 134110770 | D14: 138667087 | E14: 565202509 | G14: Intrinsic Value | H14: =C32 -> 330.35496
B15: Cash and Cash Equivalents | C15: 7334432 | D15: 2618657 | E15: 6693222811 | G15: Market Price | H15: =C2 -> 256.5
G16: Valution Result | H16: =IF(H14>H15, "Undervalued", "Overvalued") -> Undervalued
G17: Decision | H17: Buy
B18: Bangladesh Submarine Cables PLC | C18: Operating Profit | D18: Depreciation & Amortization
C19: 2304918895 | D19: 104044215
B22: 3 Quarter EPS | C22: 16.77 | E22: Sensitivity Analysis
B23: Forward EPS | C23: =(C22*4)/3 -> 22.36 | E23: P/E Ratio | F23: EPS
B24: Trailing EPS for 12 months | C24: =D2/4 +C22 -> 23.4925 | E24: =H13 -> 15819643 | F24: 27.36 | G24: 32.36 | H24: 37.36 | I24: 42.36 | J24: 47.36 | K24: 52.36
E25: 14.4 | F25: 15819647 | G25: 15819665 | H25: 15819683 | I25: 15819701 | J25: 15819719 | K25: 15819737
E26: 16.4 | F26: 15819660 | G26: 15819681 | H26: 15819701 | I26: 15819722 | J26: 15819742 | K26: 15819763
B27: Forward P/E | C27: =C2/C23 -> 11.471377 | E27: 18.4 | F27: 15819674 | G27: 15819697 | H27: 15819720 | I27: 15819743 | J27: 15819766 | K27: 15819789
B28: Trailing P/E | C28: =C2/D2 -> 9.538862 | E28: 20.4 | F28: 15819688 | G28: 15819713 | H28: 15819739 | I28: 15819764 | J28: 15819790 | K28: 15819815
B29: P/E TTM | C29: =C2/C24 -> 10.918378 | E29: 22.4 | F29: 15819701 | G29: 15819729 | H29: 15819757 | I29: 15819785 | J29: 15819813 | K29: 15819841
B30: Industry Avg P/E | C30: =H5 -> 14.062146 | E30: 24.4 | F30: 15819715 | G30: 15819746 | H30: 15819776 | I30: 15819807 | J30: 15819837 | K30: 15819868
B31: GP EPS TTM | C31: =C24 -> 23.4925
B32: Intrinsic Value | C32: =C30*C31 -> 330.35496

Sheet Ratio Comparison
A1: Company Name | B1: P/E | C1: Industry Average
A2: Grameenphone Ltd. | B2: ='[1]Relative Valution'!H2 -> 9.538862 | C2: ='[1]Relative Valution'!H5 -> 14.062146
A3: Robi Axiata PLC. | B3: ='[1]Relative Valution'!H3 -> 21.19403 | C3: ='[1]Relative Valution'!H5 -> 14.062146
A4: Bangladesh Submarine Cables PLC | B4: ='[1]Relative Valution'!H4 -> 11.453546 | C4: ='[1]Relative Valution'!H5 -> 14.062146
A7: Company Name | B7: P/B | C7: Industry Average
A8: Grameenphone Ltd. | B8: ='[1]Relative Valution'!I2 -> 5.3496882 | C8: ='[1]Relative Valution'!I5 -> 2.9726834
A9: Robi Axiata PLC. | B9: ='[1]Relative Valution'!I3 -> 2.1714802 | C9: ='[1]Relative Valution'!I5 -> 2.9726834
A10: Bangladesh Submarine Cables PLC | B10: ='[1]Relative Valution'!I4 -> 1.3968818 | C10: ='[1]Relative Valution'!I5 -> 2.9726834
A12: Company Name | B12: ROA | C12: Industry Average
A13: Grameenphone Ltd. | B13: ='[1]Relative Valution'!L2 -> 14.5 | C13: ='[1]Relative Valution'!L5 -> 9.5
A14: Robi Axiata PLC. | B14: ='[1]Relative Valution'!L3 -> 4.5 | C14: ='[1]Relative Valution'!L5 -> 9.5
A15: Bangladesh Submarine Cables PLC | B15: ='[1]Relative Valution'!L4 -> 9.5 | C15: ='[1]Relative Valution'!L5 -> 9.5
A17: Company Name | B17: ROE | C17: Industry Average
A18: Grameenphone Ltd. | B18: ='[1]Relative Valution'!M2 -> 54.8 | C18: ='[1]Relative Valution'!M5 -> 27.433333
A19: Robi Axiata PLC. | B19: ='[1]Relative Valution'!M3 -> 14 | C19: ='[1]Relative Valution'!M5 -> 27.433333
A20: Bangladesh Submarine Cables PLC | B20: ='[1]Relative Valution'!M4 -> 13.5 | C20: ='[1]Relative Valution'!M5 -> 27.433333
A22: Company Name | B22: P/E | C22: P/B | D22: P/S
A23: Grameenphone Ltd. | B23: =B2 -> 9.538862 | C23: =B8 -> 5.3496882 | D23: ='[1]Relative Valution'!J2 -> 2.8988678
A24: Robi Axiata PLC. | B24: =B3 -> 21.19403 | C24: =B9 -> 2.1714802 | D24: ='[1]Relative Valution'!J3 -> 1.4950127
A25: Bangladesh Submarine Cables PLC | B25: =B4 -> 11.453546 | C25: =B10 -> 1.3968818 | D25: ='[1]Relative Valution'!J4 -> 5.9648052

Sheet Weighted Intrinsic Value
A1: MODEL | B1: WEIGHT | C1: INTRINSIC VALUE | D1: WEIGHTED VALUE
A2: DDM (GORDON) | B2: 0.3 | C2: =DDM!C17 -> 147.43806 | D2: =C2*B2 -> 44.231419
A3: DDM (P/E) | B3: 0.2 | C3: =DDM!C21 -> 184.15891 | D3: =C3*B3 -> 36.831781
A4: FCFF (GORDON) | B4: 0.05 | C4: 1443.1532 | D4: =C4*B4 -> 72.157662
A5: FCFF (P/E) | B5: 0.05 | C5: 2378.2095 | D5: =C5*B5 -> 118.91048
A6: RELATIVE | B6: 0.4 | C6: ='Relative Valuation'!H14 -> 330.35496 | D6: =C6*B6 -> 132.14199
B7: =SUM(B2:B6) -> 1 | C7: WEIGHTED AVG INTRINSIC VALUE | D7: =SUM(D2:D6) -> 404.27332

Sheet Visualization
T1: solvency ratios | W1: dividend payout ratio of bd telcom indistry (w industry average)
A2: Net PPE/ Sales | B2: 0.88917282 | C2: 0.99030978 | D2: 1.0704097 | E2: 1.1501975 | F2: 1.1033287 | G2: 0.12955003 | J2: gross profit margin | N2: current ratio from 2020 | Q2: roa and roe (2020) | T2: debt to asset ratio | W2: growth comparison of bd telcom industry (revenue, op. and net profit growth)
A3: Gross PPE/Sales | B3: 1.3311903 | C3: 1.2823747 | D3: 1.2600004 | E3: 1.2849578 | F3: 1.3065064 | G3: 1.2859719 | J3: net profit margin | T3: debt to equity | W3: ev/ebdita ratio comparison of bd telcom industry
J4: margin comparison of bd telcom industry (gross, net, operating)\
A21: shareholder structure (corporate govenrnance)
A22: inflation vs gdp growth
A23: exchange rate comparison
A24: per capita income
A25: coverage vs usage gap
A26: data vs voice revenue share
A27: market cap of competitiors
